{"all": {"pitchers": "2", "batters": "8", "pitches": "22", "max velomax pitch velocity": "95.8", "min velomin pitch velocity": "80.8", "ff%fourseam fastball %": "31.8", "si%sinker %": "31.8", "fc%cutter %": "4.5", "fs%splitter %": "0.0", "ch%changeup %": "13.6", "sl%slider %": "18.2", "cu%curve %": "0.0", "max evmax exit velocity": "105.6", "hhhard hit": "2", "hh%hard hit %": "28.6", "brlbarrels": "0", "brl%barrel %": "0.0", "ab": "8", "avg": ".375", "h": "3", "1b": "1", "2b": "1", "3b": "0", "hr": "1", "so": "1", "bipballs in play": "7", "liveGames": 2, "totGames": 15, "updated": "2025-07-20 12:16:05.470103"}, "sf @ tor": [{"created_at": "2025-07-20 12:11:55", "player": "willy adames", "game": "sf @ tor", "hr/park": "", "pa": "4", "dt": "2025-07-20", "team": "sf", "stadium": "tor", "in": "1", "result": "GIDP", "evo": "89.4", "la": "-2", "dist": "30", "is_hh": false, "is_brl": false}, {"created_at": "2025-07-20 12:11:10", "player": "rafael devers", "game": "sf @ tor", "hr/park": "", "pa": "3", "dt": "2025-07-20", "team": "sf", "stadium": "tor", "in": "1", "result": "Lineout", "evo": "105.6", "la": "8", "dist": "183", "is_hh": true, "is_brl": false}, {"created_at": "2025-07-20 12:09:55", "player": "heliot ramos", "game": "sf @ tor", "hr/park": "", "pa": "2", "dt": "2025-07-20", "team": "sf", "stadium": "tor", "in": "1", "result": "Single", "evo": "74.0", "la": "20", "dist": "172", "is_hh": false, "is_brl": false}, {"created_at": "2025-07-20 12:09:55", "player": "jung hoo lee", "game": "sf @ tor", "hr/park": "", "pa": "1", "dt": "2025-07-20", "team": "sf", "stadium": "tor", "in": "1", "result": "Double", "evo": "86.6", "la": "60", "dist": "219", "is_hh": false, "is_brl": false}], "bal @ tb": [{"created_at": "2025-07-20 12:13:55", "player": "ryan ohearn", "game": "bal @ tb", "hr/park": "", "pa": "4", "dt": "2025-07-20", "team": "bal", "stadium": "tb", "in": "1", "result": "Groundout", "evo": "51.4", "la": "-49", "dist": "2", "is_hh": false, "is_brl": false}, {"created_at": "2025-07-20 12:12:54", "player": "gunnar henderson", "game": "bal @ tb", "hr/park": "", "pa": "3", "dt": "2025-07-20", "team": "bal", "stadium": "tb", "in": "1", "result": "Strikeout", "evo": "", "la": "", "dist": "", "is_hh": false, "is_brl": false}, {"created_at": "2025-07-20 12:12:25", "player": "jordan westburg", "game": "bal @ tb", "hr/park": "", "pa": "2", "dt": "2025-07-20", "team": "bal", "stadium": "tb", "in": "1", "result": "Flyout", "evo": "87.0", "la": "37", "dist": "298", "is_hh": false, "is_brl": false}, {"created_at": "2025-07-20 12:11:25", "player": "jackson holliday", "game": "bal @ tb", "hr/park": "1/30", "pa": "1", "dt": "2025-07-20", "team": "bal", "stadium": "tb", "in": "1", "result": "Home Run", "evo": "95.5", "la": "25", "dist": "359", "is_hh": true, "is_brl": false}], "sd @ wsh": [], "laa @ phi": [], "chw @ pit": [], "nyy @ atl": [], "cin @ nym": [], "ath @ cle": [], "kc @ mia": [], "bos @ chc": [], "min @ col": [], "hou @ sea": [], "stl @ ari": [], "mil @ lad": [], "det @ tex": []}