{"all": {"pitchers": "9", "batters": "67", "pitches": "412", "max velomax pitch velocity": "101.3", "min velomin pitch velocity": "70.9", "ff%fourseam fastball %": "35.7", "si%sinker %": "12.6", "fc%cutter %": "4.6", "fs%splitter %": "1.5", "ch%changeup %": "8.3", "sl%slider %": "23.5", "cu%curve %": "13.8", "max evmax exit velocity": "112.2", "hhhard hit": "25", "hh%hard hit %": "37.9", "brlbarrels": "7", "brl%barrel %": "10.6", "ab": "86", "avg": ".233", "h": "20", "1b": "12", "2b": "5", "3b": "1", "hr": "2", "so": "22", "bipballs in play": "66", "liveGames": 4, "totGames": 13, "updated": "2025-09-01 14:08:33.033882"}, "mia @ wsh": [{"created_at": "2025-09-01 14:05:10", "player": "daylen lile", "game": "mia @ wsh", "hr/park": "", "pa": "28", "dt": "2025-09-01", "team": "wsh", "stadium": "wsh", "bats": "L", "in": "4", "result": "Flyout", "evo": "73.1", "la": "40", "dist": "222", "is_hh": false, "is_brl": false, "pitcher": "cade gibson", "pitch": "ST", "pitcherLR": "L"}, {"created_at": "2025-09-01 14:04:56", "player": "luis garcia", "game": "mia @ wsh", "hr/park": "", "pa": "27", "dt": "2025-09-01", "team": "wsh", "stadium": "wsh", "bats": "L", "in": "4", "result": "Single", "evo": "105.2", "la": "14", "dist": "255", "is_hh": true, "is_brl": false, "pitcher": "cade gibson", "pitch": "SI", "pitcherLR": "L"}, {"created_at": "2025-09-01 14:02:26", "player": "josh bell", "game": "mia @ wsh", "hr/park": "", "pa": "26", "dt": "2025-09-01", "team": "wsh", "stadium": "wsh", "bats": "B", "in": "4", "result": "Strikeout", "evo": "", "la": "", "dist": "", "is_hh": false, "is_brl": false, "pitcher": "cade gibson", "pitch": "CU", "pitcherLR": "L"}, {"created_at": "2025-09-01 13:59:25", "player": "connor norby", "game": "mia @ wsh", "hr/park": "", "pa": "25", "dt": "2025-09-01", "team": "mia", "stadium": "wsh", "bats": "", "in": "4", "result": "Flyout", "evo": "87.0", "la": "29", "dist": "294", "is_hh": false, "is_brl": false, "pitcher": "andrew alvarez", "pitch": "FF", "pitcherLR": ""}, {"created_at": "2025-09-01 13:57:11", "player": "otto lopez", "game": "mia @ wsh", "hr/park": "", "pa": "24", "dt": "2025-09-01", "team": "mia", "stadium": "wsh", "bats": "R", "in": "4", "result": "Strikeout", "evo": "", "la": "", "dist": "", "is_hh": false, "is_brl": false, "pitcher": "andrew alvarez", "pitch": "CU", "pitcherLR": ""}, {"created_at": "2025-09-01 13:55:11", "player": "jakob marsee", "game": "mia @ wsh", "hr/park": "", "pa": "23", "dt": "2025-09-01", "team": "mia", "stadium": "wsh", "bats": "L", "in": "4", "result": "Strikeout", "evo": "", "la": "", "dist": "", "is_hh": false, "is_brl": false, "pitcher": "andrew alvarez", "pitch": "SL", "pitcherLR": ""}, {"created_at": "2025-09-01 13:52:41", "player": "cj abrams", "game": "mia @ wsh", "hr/park": "", "pa": "22", "dt": "2025-09-01", "team": "wsh", "stadium": "wsh", "bats": "L", "in": "3", "result": "Groundout", "evo": "67.2", "la": "-23", "dist": "7", "is_hh": false, "is_brl": false, "pitcher": "cade gibson", "pitch": "CU", "pitcherLR": "L"}, {"created_at": "2025-09-01 13:50:56", "player": "james wood", "game": "mia @ wsh", "hr/park": "", "pa": "21", "dt": "2025-09-01", "team": "wsh", "stadium": "wsh", "bats": "L", "in": "3", "result": "Strikeout", "evo": "", "la": "", "dist": "", "is_hh": false, "is_brl": false, "pitcher": "cade gibson", "pitch": "FF", "pitcherLR": "L"}, {"created_at": "2025-09-01 13:49:56", "player": "cj stubbs", "game": "mia @ wsh", "hr/park": "", "pa": "20", "dt": "2025-09-01", "team": "wsh", "stadium": "wsh", "bats": "", "in": "3", "result": "Pop Out", "evo": "60.3", "la": "53", "dist": "146", "is_hh": false, "is_brl": false, "pitcher": "cade gibson", "pitch": "FF", "pitcherLR": "L"}, {"created_at": "2025-09-01 13:47:27", "player": "agustin ramirez", "game": "mia @ wsh", "hr/park": "", "pa": "19", "dt": "2025-09-01", "team": "mia", "stadium": "wsh", "bats": "R", "in": "3", "result": "Pop Out", "evo": "77.0", "la": "62", "dist": "158", "is_hh": false, "is_brl": false, "pitcher": "andrew alvarez", "pitch": "CU", "pitcherLR": ""}, {"created_at": "2025-09-01 13:44:25", "player": "joey wiemer", "game": "mia @ wsh", "hr/park": "", "pa": "18", "dt": "2025-09-01", "team": "mia", "stadium": "wsh", "bats": "R", "in": "3", "result": "Strikeout", "evo": "", "la": "", "dist": "", "is_hh": false, "is_brl": false, "pitcher": "andrew alvarez", "pitch": "CU", "pitcherLR": ""}, {"created_at": "2025-09-01 13:43:10", "player": "javier sanoja", "game": "mia @ wsh", "hr/park": "", "pa": "17", "dt": "2025-09-01", "team": "mia", "stadium": "wsh", "bats": "R", "in": "3", "result": "Pop Out", "evo": "62.4", "la": "69", "dist": "86", "is_hh": false, "is_brl": false, "pitcher": "andrew alvarez", "pitch": "CH", "pitcherLR": ""}, {"created_at": "2025-09-01 13:39:56", "player": "derek hill", "game": "mia @ wsh", "hr/park": "", "pa": "16", "dt": "2025-09-01", "team": "mia", "stadium": "wsh", "bats": "R", "in": "3", "result": "Field Error", "evo": "97.1", "la": "-6", "dist": "17", "is_hh": true, "is_brl": false, "pitcher": "andrew alvarez", "pitch": "CH", "pitcherLR": ""}, {"created_at": "2025-09-01 13:36:26", "player": "brady house", "game": "mia @ wsh", "hr/park": "", "pa": "15", "dt": "2025-09-01", "team": "wsh", "stadium": "wsh", "bats": "R", "in": "2", "result": "Strikeout", "evo": "", "la": "", "dist": "", "is_hh": false, "is_brl": false, "pitcher": "lake bachar", "pitch": "SL", "pitcherLR": "R"}, {"created_at": "2025-09-01 13:34:26", "player": "robert hassell", "game": "mia @ wsh", "hr/park": "", "pa": "14", "dt": "2025-09-01", "team": "wsh", "stadium": "wsh", "bats": "L", "in": "2", "result": "Strikeout", "evo": "", "la": "", "dist": "", "is_hh": false, "is_brl": false, "pitcher": "lake bachar", "pitch": "FF", "pitcherLR": "R"}, {"created_at": "2025-09-01 13:33:25", "player": "andres chaparro", "game": "mia @ wsh", "hr/park": "0/30", "pa": "13", "dt": "2025-09-01", "team": "wsh", "stadium": "wsh", "bats": "R", "in": "2", "result": "Sac Fly", "evo": "95.8", "la": "28", "dist": "342", "is_hh": true, "is_brl": false, "pitcher": "lake bachar", "pitch": "ST", "pitcherLR": "R"}, {"created_at": "2025-09-01 13:30:55", "player": "daylen lile", "game": "mia @ wsh", "hr/park": "0/30", "pa": "12", "dt": "2025-09-01", "team": "wsh", "stadium": "wsh", "bats": "L", "in": "2", "result": "Triple", "evo": "98.6", "la": "26", "dist": "362", "is_hh": true, "is_brl": true, "pitcher": "lake bachar", "pitch": "FF", "pitcherLR": "R"}, {"created_at": "2025-09-01 13:28:55", "player": "luis garcia", "game": "mia @ wsh", "hr/park": "", "pa": "11", "dt": "2025-09-01", "team": "wsh", "stadium": "wsh", "bats": "L", "in": "2", "result": "Single", "evo": "102.5", "la": "12", "dist": "226", "is_hh": true, "is_brl": false, "pitcher": "lake bachar", "pitch": "SL", "pitcherLR": "R"}, {"created_at": "2025-09-01 13:25:10", "player": "eric wagaman", "game": "mia @ wsh", "hr/park": "", "pa": "10", "dt": "2025-09-01", "team": "mia", "stadium": "wsh", "bats": "R", "in": "2", "result": "Forceout", "evo": "87.9", "la": "-30", "dist": "7", "is_hh": false, "is_brl": false, "pitcher": "andrew alvarez", "pitch": "CU", "pitcherLR": ""}, {"created_at": "2025-09-01 13:22:56", "player": "heriberto hernandez", "game": "mia @ wsh", "hr/park": "", "pa": "9", "dt": "2025-09-01", "team": "mia", "stadium": "wsh", "bats": "R", "in": "2", "result": "Flyout", "evo": "81.5", "la": "30", "dist": "270", "is_hh": false, "is_brl": false, "pitcher": "andrew alvarez", "pitch": "SL", "pitcherLR": ""}, {"created_at": "2025-09-01 13:21:42", "player": "connor norby", "game": "mia @ wsh", "hr/park": "", "pa": "8", "dt": "2025-09-01", "team": "mia", "stadium": "wsh", "bats": "", "in": "2", "result": "Walk", "evo": "", "la": "", "dist": "", "is_hh": false, "is_brl": false, "pitcher": "andrew alvarez", "pitch": "SI", "pitcherLR": ""}, {"created_at": "2025-09-01 13:20:40", "player": "otto lopez", "game": "mia @ wsh", "hr/park": "", "pa": "7", "dt": "2025-09-01", "team": "mia", "stadium": "wsh", "bats": "R", "in": "2", "result": "Groundout", "evo": "78.0", "la": "-8", "dist": "16", "is_hh": false, "is_brl": false, "pitcher": "andrew alvarez", "pitch": "SL", "pitcherLR": ""}, {"created_at": "2025-09-01 13:17:26", "player": "josh bell", "game": "mia @ wsh", "hr/park": "", "pa": "6", "dt": "2025-09-01", "team": "wsh", "stadium": "wsh", "bats": "B", "in": "1", "result": "Groundout", "evo": "76.0", "la": "-15", "dist": "8", "is_hh": false, "is_brl": false, "pitcher": "lake bachar", "pitch": "SL", "pitcherLR": "R"}, {"created_at": "2025-09-01 13:14:41", "player": "cj abrams", "game": "mia @ wsh", "hr/park": "", "pa": "5", "dt": "2025-09-01", "team": "wsh", "stadium": "wsh", "bats": "L", "in": "1", "result": "Flyout", "evo": "87.5", "la": "54", "dist": "256", "is_hh": false, "is_brl": false, "pitcher": "lake bachar", "pitch": "SL", "pitcherLR": "R"}, {"created_at": "2025-09-01 13:14:41", "player": "james wood", "game": "mia @ wsh", "hr/park": "", "pa": "4", "dt": "2025-09-01", "team": "wsh", "stadium": "wsh", "bats": "L", "in": "1", "result": "Groundout", "evo": "80.6", "la": "13", "dist": "139", "is_hh": false, "is_brl": false, "pitcher": "lake bachar", "pitch": "FF", "pitcherLR": "R"}, {"created_at": "2025-09-01 13:10:42", "player": "jakob marsee", "game": "mia @ wsh", "hr/park": "", "pa": "3", "dt": "2025-09-01", "team": "mia", "stadium": "wsh", "bats": "L", "in": "1", "result": "Flyout", "evo": "84.4", "la": "29", "dist": "282", "is_hh": false, "is_brl": false, "pitcher": "andrew alvarez", "pitch": "SL", "pitcherLR": ""}, {"created_at": "2025-09-01 13:09:41", "player": "agustin ramirez", "game": "mia @ wsh", "hr/park": "", "pa": "2", "dt": "2025-09-01", "team": "mia", "stadium": "wsh", "bats": "R", "in": "1", "result": "Groundout", "evo": "51.8", "la": "-38", "dist": "4", "is_hh": false, "is_brl": false, "pitcher": "andrew alvarez", "pitch": "SL", "pitcherLR": ""}, {"created_at": "2025-09-01 13:09:41", "player": "xavier edwards", "game": "mia @ wsh", "hr/park": "", "pa": "1", "dt": "2025-09-01", "team": "mia", "stadium": "wsh", "bats": "B", "in": "1", "result": "Groundout", "evo": "55.2", "la": "-76", "dist": "2", "is_hh": false, "is_brl": false, "pitcher": "andrew alvarez", "pitch": "CU", "pitcherLR": ""}], "nym @ det": [{"created_at": "2025-09-01 14:08:27", "player": "jeff mcneil", "game": "nym @ det", "hr/park": "", "pa": "29", "dt": "2025-09-01", "team": "nym", "stadium": "det", "bats": "L", "in": "4", "result": "In Progress", "evo": "", "la": "", "dist": "", "is_hh": false, "is_brl": false, "pitcher": "charlie morton", "pitch": "SI", "pitcherLR": "R"}, {"created_at": "2025-09-01 14:05:25", "player": "riley greene", "game": "nym @ det", "hr/park": "", "pa": "28", "dt": "2025-09-01", "team": "det", "stadium": "det", "bats": "L", "in": "3", "result": "Groundout", "evo": "103.5", "la": "-13", "dist": "7", "is_hh": true, "is_brl": false, "pitcher": "sean manaea", "pitch": "FF", "pitcherLR": "L"}, {"created_at": "2025-09-01 14:04:41", "player": "spencer torkelson", "game": "nym @ det", "hr/park": "", "pa": "27", "dt": "2025-09-01", "team": "det", "stadium": "det", "bats": "R", "in": "3", "result": "Strikeout", "evo": "", "la": "", "dist": "", "is_hh": false, "is_brl": false, "pitcher": "sean manaea", "pitch": "FF", "pitcherLR": "L"}, {"created_at": "2025-09-01 14:03:27", "player": "wenceel perez", "game": "nym @ det", "hr/park": "30/30", "pa": "26", "dt": "2025-09-01", "team": "det", "stadium": "det", "bats": "B", "in": "3", "result": "Home Run", "evo": "106.4", "la": "26", "dist": "411", "is_hh": true, "is_brl": true, "pitcher": "sean manaea", "pitch": "ST", "pitcherLR": "L"}, {"created_at": "2025-09-01 14:01:40", "player": "gleyber torres", "game": "nym @ det", "hr/park": "", "pa": "25", "dt": "2025-09-01", "team": "det", "stadium": "det", "bats": "R", "in": "3", "result": "Walk", "evo": "", "la": "", "dist": "", "is_hh": false, "is_brl": false, "pitcher": "sean manaea", "pitch": "FF", "pitcherLR": "L"}, {"created_at": "2025-09-01 14:01:40", "player": "jahmai jones", "game": "nym @ det", "hr/park": "0/30", "pa": "24", "dt": "2025-09-01", "team": "det", "stadium": "det", "bats": "R", "in": "3", "result": "Flyout", "evo": "100.1", "la": "46", "dist": "303", "is_hh": true, "is_brl": false, "pitcher": "sean manaea", "pitch": "FF", "pitcherLR": "L"}, {"created_at": "2025-09-01 13:59:25", "player": "mark vientos", "game": "nym @ det", "hr/park": "", "pa": "23", "dt": "2025-09-01", "team": "nym", "stadium": "det", "bats": "R", "in": "3", "result": "Groundout", "evo": "97.2", "la": "-19", "dist": "8", "is_hh": true, "is_brl": false, "pitcher": "charlie morton", "pitch": "SI", "pitcherLR": "R"}, {"created_at": "2025-09-01 13:59:25", "player": "brandon nimmo", "game": "nym @ det", "hr/park": "", "pa": "22", "dt": "2025-09-01", "team": "nym", "stadium": "det", "bats": "L", "in": "3", "result": "Groundout", "evo": "108.8", "la": "4", "dist": "97", "is_hh": true, "is_brl": false, "pitcher": "charlie morton", "pitch": "FF", "pitcherLR": "R"}, {"created_at": "2025-09-01 13:56:56", "player": "pete alonso", "game": "nym @ det", "hr/park": "0/30", "pa": "21", "dt": "2025-09-01", "team": "nym", "stadium": "det", "bats": "R", "in": "3", "result": "Lineout", "evo": "108.2", "la": "17", "dist": "349", "is_hh": true, "is_brl": true, "pitcher": "charlie morton", "pitch": "SI", "pitcherLR": "R"}, {"created_at": "2025-09-01 13:53:40", "player": "javier baez", "game": "nym @ det", "hr/park": "", "pa": "20", "dt": "2025-09-01", "team": "det", "stadium": "det", "bats": "R", "in": "2", "result": "Groundout", "evo": "100.6", "la": "-4", "dist": "31", "is_hh": true, "is_brl": false, "pitcher": "sean manaea", "pitch": "FF", "pitcherLR": "L"}, {"created_at": "2025-09-01 13:51:55", "player": "zach mckinstry", "game": "nym @ det", "hr/park": "", "pa": "19", "dt": "2025-09-01", "team": "det", "stadium": "det", "bats": "L", "in": "2", "result": "Forceout", "evo": "73.4", "la": "9", "dist": "101", "is_hh": false, "is_brl": false, "pitcher": "sean manaea", "pitch": "ST", "pitcherLR": "L"}, {"created_at": "2025-09-01 13:49:42", "player": "dillon dingler", "game": "nym @ det", "hr/park": "", "pa": "18", "dt": "2025-09-01", "team": "det", "stadium": "det", "bats": "R", "in": "2", "result": "Single", "evo": "89.9", "la": "10", "dist": "162", "is_hh": false, "is_brl": false, "pitcher": "sean manaea", "pitch": "CH", "pitcherLR": "L"}, {"created_at": "2025-09-01 13:47:55", "player": "andy ibanez", "game": "nym @ det", "hr/park": "", "pa": "17", "dt": "2025-09-01", "team": "det", "stadium": "det", "bats": "R", "in": "2", "result": "Strikeout", "evo": "", "la": "", "dist": "", "is_hh": false, "is_brl": false, "pitcher": "sean manaea", "pitch": "ST", "pitcherLR": "L"}, {"created_at": "2025-09-01 13:45:55", "player": "riley greene", "game": "nym @ det", "hr/park": "", "pa": "16", "dt": "2025-09-01", "team": "det", "stadium": "det", "bats": "L", "in": "2", "result": "Single", "evo": "97.4", "la": "4", "dist": "82", "is_hh": true, "is_brl": false, "pitcher": "sean manaea", "pitch": "FF", "pitcherLR": "L"}, {"created_at": "2025-09-01 13:42:26", "player": "juan soto", "game": "nym @ det", "hr/park": "", "pa": "15", "dt": "2025-09-01", "team": "nym", "stadium": "det", "bats": "L", "in": "2", "result": "Strikeout", "evo": "", "la": "", "dist": "", "is_hh": false, "is_brl": false, "pitcher": "charlie morton", "pitch": "CU", "pitcherLR": "R"}, {"created_at": "2025-09-01 13:38:56", "player": "francisco lindor", "game": "nym @ det", "hr/park": "0/30", "pa": "14", "dt": "2025-09-01", "team": "nym", "stadium": "det", "bats": "B", "in": "2", "result": "Flyout", "evo": "94.8", "la": "33", "dist": "338", "is_hh": false, "is_brl": false, "pitcher": "charlie morton", "pitch": "CU", "pitcherLR": "R"}, {"created_at": "2025-09-01 13:35:56", "player": "brett baty", "game": "nym @ det", "hr/park": "", "pa": "13", "dt": "2025-09-01", "team": "nym", "stadium": "det", "bats": "L", "in": "2", "result": "Walk", "evo": "", "la": "", "dist": "", "is_hh": false, "is_brl": false, "pitcher": "charlie morton", "pitch": "CU", "pitcherLR": "R"}, {"created_at": "2025-09-01 13:35:10", "player": "luis torrens", "game": "nym @ det", "hr/park": "", "pa": "12", "dt": "2025-09-01", "team": "nym", "stadium": "det", "bats": "R", "in": "2", "result": "Double", "evo": "93.9", "la": "3", "dist": "70", "is_hh": false, "is_brl": false, "pitcher": "charlie morton", "pitch": "FC", "pitcherLR": "R"}, {"created_at": "2025-09-01 13:33:40", "player": "cedric mullins", "game": "nym @ det", "hr/park": "", "pa": "11", "dt": "2025-09-01", "team": "nym", "stadium": "det", "bats": "L", "in": "2", "result": "Sac Bunt", "evo": "32.0", "la": "-66", "dist": "2", "is_hh": false, "is_brl": false, "pitcher": "charlie morton", "pitch": "CH", "pitcherLR": "R"}, {"created_at": "2025-09-01 13:30:55", "player": "jeff mcneil", "game": "nym @ det", "hr/park": "", "pa": "10", "dt": "2025-09-01", "team": "nym", "stadium": "det", "bats": "L", "in": "2", "result": "Single", "evo": "98.3", "la": "6", "dist": "109", "is_hh": true, "is_brl": false, "pitcher": "charlie morton", "pitch": "CU", "pitcherLR": "R"}, {"created_at": "2025-09-01 13:29:12", "player": "mark vientos", "game": "nym @ det", "hr/park": "", "pa": "9", "dt": "2025-09-01", "team": "nym", "stadium": "det", "bats": "R", "in": "2", "result": "Hit By Pitch", "evo": "", "la": "", "dist": "", "is_hh": false, "is_brl": false, "pitcher": "charlie morton", "pitch": "FF", "pitcherLR": "R"}, {"created_at": "2025-09-01 13:25:41", "player": "spencer torkelson", "game": "nym @ det", "hr/park": "", "pa": "8", "dt": "2025-09-01", "team": "det", "stadium": "det", "bats": "R", "in": "1", "result": "Pop Out", "evo": "86.7", "la": "75", "dist": "39", "is_hh": false, "is_brl": false, "pitcher": "sean manaea", "pitch": "ST", "pitcherLR": "L"}, {"created_at": "2025-09-01 13:22:41", "player": "wenceel perez", "game": "nym @ det", "hr/park": "", "pa": "7", "dt": "2025-09-01", "team": "det", "stadium": "det", "bats": "B", "in": "1", "result": "Strikeout", "evo": "", "la": "", "dist": "", "is_hh": false, "is_brl": false, "pitcher": "sean manaea", "pitch": "FF", "pitcherLR": "L"}, {"created_at": "2025-09-01 13:21:55", "player": "gleyber torres", "game": "nym @ det", "hr/park": "", "pa": "6", "dt": "2025-09-01", "team": "det", "stadium": "det", "bats": "R", "in": "1", "result": "Strikeout", "evo": "", "la": "", "dist": "", "is_hh": false, "is_brl": false, "pitcher": "sean manaea", "pitch": "ST", "pitcherLR": "L"}, {"created_at": "2025-09-01 13:20:55", "player": "jahmai jones", "game": "nym @ det", "hr/park": "30/30", "pa": "5", "dt": "2025-09-01", "team": "det", "stadium": "det", "bats": "R", "in": "1", "result": "Home Run", "evo": "108.5", "la": "27", "dist": "429", "is_hh": true, "is_brl": true, "pitcher": "sean manaea", "pitch": "FF", "pitcherLR": "L"}, {"created_at": "2025-09-01 13:16:55", "player": "brandon nimmo", "game": "nym @ det", "hr/park": "", "pa": "4", "dt": "2025-09-01", "team": "nym", "stadium": "det", "bats": "L", "in": "1", "result": "Groundout", "evo": "87.0", "la": "-28", "dist": "6", "is_hh": false, "is_brl": false, "pitcher": "charlie morton", "pitch": "FC", "pitcherLR": "R"}, {"created_at": "2025-09-01 13:15:12", "player": "pete alonso", "game": "nym @ det", "hr/park": "", "pa": "3", "dt": "2025-09-01", "team": "nym", "stadium": "det", "bats": "R", "in": "1", "result": "GIDP", "evo": "79.9", "la": "-2", "dist": "29", "is_hh": false, "is_brl": false, "pitcher": "charlie morton", "pitch": "CU", "pitcherLR": "R"}, {"created_at": "2025-09-01 13:12:41", "player": "juan soto", "game": "nym @ det", "hr/park": "", "pa": "2", "dt": "2025-09-01", "team": "nym", "stadium": "det", "bats": "L", "in": "1", "result": "Walk", "evo": "", "la": "", "dist": "", "is_hh": false, "is_brl": false, "pitcher": "charlie morton", "pitch": "CU", "pitcherLR": "R"}, {"created_at": "2025-09-01 13:12:25", "player": "francisco lindor", "game": "nym @ det", "hr/park": "", "pa": "1", "dt": "2025-09-01", "team": "nym", "stadium": "det", "bats": "B", "in": "1", "result": "Walk", "evo": "", "la": "", "dist": "", "is_hh": false, "is_brl": false, "pitcher": "charlie morton", "pitch": "FF", "pitcherLR": "R"}], "tor @ cin": [{"created_at": "2025-09-01 14:05:10", "player": "daulton varsho", "game": "tor @ cin", "hr/park": "", "pa": "26", "dt": "2025-09-01", "team": "tor", "stadium": "cin", "bats": "L", "in": "4", "result": "Strikeout", "evo": "", "la": "", "dist": "", "is_hh": false, "is_brl": false, "pitcher": "hunter greene", "pitch": "SL", "pitcherLR": "R"}, {"created_at": "2025-09-01 14:03:56", "player": "bo bichette", "game": "tor @ cin", "hr/park": "", "pa": "25", "dt": "2025-09-01", "team": "tor", "stadium": "cin", "bats": "R", "in": "4", "result": "Single", "evo": "101.8", "la": "9", "dist": "210", "is_hh": true, "is_brl": false, "pitcher": "hunter greene", "pitch": "FF", "pitcherLR": "R"}, {"created_at": "2025-09-01 14:01:25", "player": "vladimir guerrero", "game": "tor @ cin", "hr/park": "", "pa": "24", "dt": "2025-09-01", "team": "tor", "stadium": "cin", "bats": "R", "in": "4", "result": "Groundout", "evo": "41.4", "la": "-36", "dist": "4", "is_hh": false, "is_brl": false, "pitcher": "hunter greene", "pitch": "FF", "pitcherLR": "R"}, {"created_at": "2025-09-01 13:59:12", "player": "addison barger", "game": "tor @ cin", "hr/park": "", "pa": "23", "dt": "2025-09-01", "team": "tor", "stadium": "cin", "bats": "L", "in": "4", "result": "Strikeout", "evo": "", "la": "", "dist": "", "is_hh": false, "is_brl": false, "pitcher": "hunter greene", "pitch": "SL", "pitcherLR": "R"}, {"created_at": "2025-09-01 13:56:56", "player": "elly de la cruz", "game": "tor @ cin", "hr/park": "", "pa": "22", "dt": "2025-09-01", "team": "cin", "stadium": "cin", "bats": "B", "in": "3", "result": "Groundout", "evo": "91.5", "la": "-26", "dist": "9", "is_hh": false, "is_brl": false, "pitcher": "chris bassitt", "pitch": "FC", "pitcherLR": "R"}, {"created_at": "2025-09-01 13:54:41", "player": "noelvi marte", "game": "tor @ cin", "hr/park": "", "pa": "21", "dt": "2025-09-01", "team": "cin", "stadium": "cin", "bats": "R", "in": "3", "result": "Strikeout", "evo": "", "la": "", "dist": "", "is_hh": false, "is_brl": false, "pitcher": "chris bassitt", "pitch": "ST", "pitcherLR": "R"}, {"created_at": "2025-09-01 13:53:11", "player": "tj friedl", "game": "tor @ cin", "hr/park": "", "pa": "20", "dt": "2025-09-01", "team": "cin", "stadium": "cin", "bats": "L", "in": "3", "result": "Flyout", "evo": "67.7", "la": "44", "dist": "212", "is_hh": false, "is_brl": false, "pitcher": "chris bassitt", "pitch": "ST", "pitcherLR": "R"}, {"created_at": "2025-09-01 13:50:11", "player": "george springer", "game": "tor @ cin", "hr/park": "", "pa": "19", "dt": "2025-09-01", "team": "tor", "stadium": "cin", "bats": "R", "in": "3", "result": "Strikeout", "evo": "", "la": "", "dist": "", "is_hh": false, "is_brl": false, "pitcher": "hunter greene", "pitch": "SL", "pitcherLR": "R"}, {"created_at": "2025-09-01 13:49:42", "player": "andres gimenez", "game": "tor @ cin", "hr/park": "0/30", "pa": "18", "dt": "2025-09-01", "team": "tor", "stadium": "cin", "bats": "L", "in": "3", "result": "Flyout", "evo": "90.7", "la": "28", "dist": "334", "is_hh": false, "is_brl": false, "pitcher": "hunter greene", "pitch": "FF", "pitcherLR": "R"}, {"created_at": "2025-09-01 13:47:10", "player": "ernie clement", "game": "tor @ cin", "hr/park": "0/30", "pa": "17", "dt": "2025-09-01", "team": "tor", "stadium": "cin", "bats": "R", "in": "3", "result": "Flyout", "evo": "86.9", "la": "32", "dist": "313", "is_hh": false, "is_brl": false, "pitcher": "hunter greene", "pitch": "FF", "pitcherLR": "R"}, {"created_at": "2025-09-01 13:44:25", "player": "matt mclain", "game": "tor @ cin", "hr/park": "", "pa": "16", "dt": "2025-09-01", "team": "cin", "stadium": "cin", "bats": "R", "in": "2", "result": "Double Play", "evo": "78.6", "la": "29", "dist": "278", "is_hh": false, "is_brl": false, "pitcher": "chris bassitt", "pitch": "CU", "pitcherLR": "R"}, {"created_at": "2025-09-01 13:43:42", "player": "jose trevino", "game": "tor @ cin", "hr/park": "", "pa": "15", "dt": "2025-09-01", "team": "cin", "stadium": "cin", "bats": "R", "in": "2", "result": "Groundout", "evo": "95.2", "la": "-10", "dist": "14", "is_hh": true, "is_brl": false, "pitcher": "chris bassitt", "pitch": "SI", "pitcherLR": "R"}, {"created_at": "2025-09-01 13:41:25", "player": "kebryan hayes", "game": "tor @ cin", "hr/park": "4/30", "pa": "14", "dt": "2025-09-01", "team": "cin", "stadium": "cin", "bats": "R", "in": "2", "result": "Double", "evo": "97.8", "la": "28", "dist": "388", "is_hh": true, "is_brl": false, "pitcher": "chris bassitt", "pitch": "CU", "pitcherLR": "R"}, {"created_at": "2025-09-01 13:39:11", "player": "sal stewart", "game": "tor @ cin", "hr/park": "", "pa": "13", "dt": "2025-09-01", "team": "cin", "stadium": "cin", "bats": "", "in": "2", "result": "Single", "evo": "76.8", "la": "17", "dist": "197", "is_hh": false, "is_brl": false, "pitcher": "chris bassitt", "pitch": "ST", "pitcherLR": "R"}, {"created_at": "2025-09-01 13:36:55", "player": "gavin lux", "game": "tor @ cin", "hr/park": "0/30", "pa": "12", "dt": "2025-09-01", "team": "cin", "stadium": "cin", "bats": "L", "in": "2", "result": "Double", "evo": "89.8", "la": "26", "dist": "333", "is_hh": false, "is_brl": false, "pitcher": "chris bassitt", "pitch": "FC", "pitcherLR": "R"}, {"created_at": "2025-09-01 13:34:10", "player": "nathan lukes", "game": "tor @ cin", "hr/park": "", "pa": "11", "dt": "2025-09-01", "team": "tor", "stadium": "cin", "bats": "L", "in": "2", "result": "Strikeout", "evo": "", "la": "", "dist": "", "is_hh": false, "is_brl": false, "pitcher": "hunter greene", "pitch": "FF", "pitcherLR": "R"}, {"created_at": "2025-09-01 13:32:55", "player": "alejandro kirk", "game": "tor @ cin", "hr/park": "", "pa": "10", "dt": "2025-09-01", "team": "tor", "stadium": "cin", "bats": "R", "in": "2", "result": "Strikeout", "evo": "", "la": "", "dist": "", "is_hh": false, "is_brl": false, "pitcher": "hunter greene", "pitch": "FF", "pitcherLR": "R"}, {"created_at": "2025-09-01 13:31:42", "player": "daulton varsho", "game": "tor @ cin", "hr/park": "1/30", "pa": "9", "dt": "2025-09-01", "team": "tor", "stadium": "cin", "bats": "L", "in": "2", "result": "Flyout", "evo": "98.4", "la": "26", "dist": "384", "is_hh": true, "is_brl": true, "pitcher": "hunter greene", "pitch": "SL", "pitcherLR": "R"}, {"created_at": "2025-09-01 13:29:56", "player": "bo bichette", "game": "tor @ cin", "hr/park": "1/30", "pa": "8", "dt": "2025-09-01", "team": "tor", "stadium": "cin", "bats": "R", "in": "2", "result": "Double", "evo": "103.9", "la": "21", "dist": "396", "is_hh": true, "is_brl": true, "pitcher": "hunter greene", "pitch": "SL", "pitcherLR": "R"}, {"created_at": "2025-09-01 13:26:55", "player": "austin hays", "game": "tor @ cin", "hr/park": "", "pa": "7", "dt": "2025-09-01", "team": "cin", "stadium": "cin", "bats": "R", "in": "1", "result": "Forceout", "evo": "93.6", "la": "-13", "dist": "15", "is_hh": false, "is_brl": false, "pitcher": "chris bassitt", "pitch": "SI", "pitcherLR": "R"}, {"created_at": "2025-09-01 13:24:12", "player": "elly de la cruz", "game": "tor @ cin", "hr/park": "", "pa": "6", "dt": "2025-09-01", "team": "cin", "stadium": "cin", "bats": "B", "in": "1", "result": "Strikeout", "evo": "", "la": "", "dist": "", "is_hh": false, "is_brl": false, "pitcher": "chris bassitt", "pitch": "SI", "pitcherLR": "R"}, {"created_at": "2025-09-01 13:20:40", "player": "noelvi marte", "game": "tor @ cin", "hr/park": "", "pa": "5", "dt": "2025-09-01", "team": "cin", "stadium": "cin", "bats": "R", "in": "1", "result": "Strikeout", "evo": "", "la": "", "dist": "", "is_hh": false, "is_brl": false, "pitcher": "chris bassitt", "pitch": "CU", "pitcherLR": "R"}, {"created_at": "2025-09-01 13:19:40", "player": "tj friedl", "game": "tor @ cin", "hr/park": "", "pa": "4", "dt": "2025-09-01", "team": "cin", "stadium": "cin", "bats": "L", "in": "1", "result": "Walk", "evo": "", "la": "", "dist": "", "is_hh": false, "is_brl": false, "pitcher": "chris bassitt", "pitch": "SI", "pitcherLR": "R"}, {"created_at": "2025-09-01 13:15:41", "player": "vladimir guerrero", "game": "tor @ cin", "hr/park": "", "pa": "3", "dt": "2025-09-01", "team": "tor", "stadium": "cin", "bats": "R", "in": "1", "result": "Flyout", "evo": "66.2", "la": "40", "dist": "204", "is_hh": false, "is_brl": false, "pitcher": "hunter greene", "pitch": "FF", "pitcherLR": "R"}, {"created_at": "2025-09-01 13:13:41", "player": "addison barger", "game": "tor @ cin", "hr/park": "", "pa": "2", "dt": "2025-09-01", "team": "tor", "stadium": "cin", "bats": "L", "in": "1", "result": "Double Play", "evo": "103.4", "la": "8", "dist": "200", "is_hh": true, "is_brl": false, "pitcher": "hunter greene", "pitch": "FS", "pitcherLR": "R"}, {"created_at": "2025-09-01 13:12:55", "player": "george springer", "game": "tor @ cin", "hr/park": "", "pa": "1", "dt": "2025-09-01", "team": "tor", "stadium": "cin", "bats": "R", "in": "1", "result": "Single", "evo": "112.2", "la": "12", "dist": "271", "is_hh": true, "is_brl": true, "pitcher": "hunter greene", "pitch": "FF", "pitcherLR": "R"}], "cle @ bos": [{"created_at": "2025-09-01 14:07:10", "player": "bo naylor", "game": "cle @ bos", "hr/park": "", "pa": "12", "dt": "2025-09-01", "team": "cle", "stadium": "bos", "bats": "L", "in": "2", "result": "In Progress", "evo": "", "la": "", "dist": "", "is_hh": false, "is_brl": false, "pitcher": "brayan bello", "pitch": "FF", "pitcherLR": "R"}, {"created_at": "2025-09-01 14:01:57", "player": "ceddanne rafaela", "game": "cle @ bos", "hr/park": "", "pa": "11", "dt": "2025-09-01", "team": "bos", "stadium": "bos", "bats": "R", "in": "1", "result": "Flyout", "evo": "89.3", "la": "36", "dist": "296", "is_hh": false, "is_brl": false, "pitcher": "parker messick", "pitch": "SL", "pitcherLR": "L"}, {"created_at": "2025-09-01 14:00:27", "player": "nate eaton", "game": "cle @ bos", "hr/park": "", "pa": "10", "dt": "2025-09-01", "team": "bos", "stadium": "bos", "bats": "R", "in": "1", "result": "Single", "evo": "92.1", "la": "-15", "dist": "6", "is_hh": false, "is_brl": false, "pitcher": "parker messick", "pitch": "CH", "pitcherLR": "L"}, {"created_at": "2025-09-01 13:57:56", "player": "rob refsnyder", "game": "cle @ bos", "hr/park": "", "pa": "9", "dt": "2025-09-01", "team": "bos", "stadium": "bos", "bats": "R", "in": "1", "result": "Strikeout", "evo": "", "la": "", "dist": "", "is_hh": false, "is_brl": false, "pitcher": "parker messick", "pitch": "SL", "pitcherLR": "L"}, {"created_at": "2025-09-01 13:56:41", "player": "romy gonzalez", "game": "cle @ bos", "hr/park": "", "pa": "8", "dt": "2025-09-01", "team": "bos", "stadium": "bos", "bats": "R", "in": "1", "result": "Single", "evo": "93.8", "la": "13", "dist": "224", "is_hh": false, "is_brl": false, "pitcher": "parker messick", "pitch": "FF", "pitcherLR": "L"}, {"created_at": "2025-09-01 13:54:12", "player": "trevor story", "game": "cle @ bos", "hr/park": "", "pa": "7", "dt": "2025-09-01", "team": "bos", "stadium": "bos", "bats": "R", "in": "1", "result": "Groundout", "evo": "77.8", "la": "-9", "dist": "15", "is_hh": false, "is_brl": false, "pitcher": "parker messick", "pitch": "CH", "pitcherLR": "L"}, {"created_at": "2025-09-01 13:51:12", "player": "alex bregman", "game": "cle @ bos", "hr/park": "0/30", "pa": "6", "dt": "2025-09-01", "team": "bos", "stadium": "bos", "bats": "R", "in": "1", "result": "Double", "evo": "103.1", "la": "20", "dist": "368", "is_hh": true, "is_brl": false, "pitcher": "parker messick", "pitch": "FF", "pitcherLR": "L"}, {"created_at": "2025-09-01 13:50:56", "player": "roman anthony", "game": "cle @ bos", "hr/park": "", "pa": "5", "dt": "2025-09-01", "team": "bos", "stadium": "bos", "bats": "L", "in": "1", "result": "Single", "evo": "106.6", "la": "-9", "dist": "17", "is_hh": true, "is_brl": false, "pitcher": "parker messick", "pitch": "SI", "pitcherLR": "L"}, {"created_at": "2025-09-01 13:45:10", "player": "kyle manzardo", "game": "cle @ bos", "hr/park": "", "pa": "4", "dt": "2025-09-01", "team": "cle", "stadium": "bos", "bats": "L", "in": "1", "result": "Strikeout", "evo": "", "la": "", "dist": "", "is_hh": false, "is_brl": false, "pitcher": "brayan bello", "pitch": "CH", "pitcherLR": "R"}, {"created_at": "2025-09-01 13:42:26", "player": "jose ramirez", "game": "cle @ bos", "hr/park": "", "pa": "3", "dt": "2025-09-01", "team": "cle", "stadium": "bos", "bats": "B", "in": "1", "result": "Lineout", "evo": "93.9", "la": "17", "dist": "293", "is_hh": false, "is_brl": false, "pitcher": "brayan bello", "pitch": "CH", "pitcherLR": "R"}, {"created_at": "2025-09-01 13:39:56", "player": "daniel schneemann", "game": "cle @ bos", "hr/park": "", "pa": "2", "dt": "2025-09-01", "team": "cle", "stadium": "bos", "bats": "L", "in": "1", "result": "Forceout", "evo": "99.9", "la": "-2", "dist": "35", "is_hh": true, "is_brl": false, "pitcher": "brayan bello", "pitch": "FC", "pitcherLR": "R"}, {"created_at": "2025-09-01 13:38:40", "player": "steven kwan", "game": "cle @ bos", "hr/park": "", "pa": "1", "dt": "2025-09-01", "team": "cle", "stadium": "bos", "bats": "L", "in": "1", "result": "Single", "evo": "94.3", "la": "11", "dist": "147", "is_hh": false, "is_brl": false, "pitcher": "brayan bello", "pitch": "ST", "pitcherLR": "R"}], "laa @ hou": [], "chw @ min": [], "ath @ stl": [], "atl @ chc": [], "sf @ col": [], "phi @ mil": [], "bal @ sd": [], "sea @ tb": [], "tex @ ari": []}