{"all": {"pitchers": "2", "batters": "5", "pitches": "12", "max velomax pitch velocity": "95.2", "min velomin pitch velocity": "83.6", "ff%fourseam fastball %": "41.7", "si%sinker %": "0.0", "fc%cutter %": "0.0", "fs%splitter %": "41.7", "ch%changeup %": "0.0", "sl%slider %": "16.7", "cu%curve %": "0.0", "max evmax exit velocity": "104.8", "hhhard hit": "1", "hh%hard hit %": "33.3", "brlbarrels": "1", "brl%barrel %": "33.3", "ab": "5", "avg": ".200", "h": "1", "1b": "0", "2b": "0", "3b": "0", "hr": "1", "so": "0", "bipballs in play": "3", "liveGames": 3, "totGames": 15, "updated": "2025-08-29 18:47:09.119288"}, "stl @ cin": [{"created_at": "2025-08-29 18:47:07", "player": "nolan gorman", "game": "stl @ cin", "hr/park": "", "pa": "4", "dt": "2025-08-29", "team": "stl", "stadium": "cin", "bats": "L", "in": "1", "result": "In Progress", "evo": "", "la": "", "dist": "", "is_hh": false, "is_brl": false, "pitcher": "zack littell", "pitch": "FF", "pitcherLR": "R"}, {"created_at": "2025-08-29 18:45:38", "player": "willson contreras", "game": "stl @ cin", "hr/park": "", "pa": "3", "dt": "2025-08-29", "team": "stl", "stadium": "cin", "bats": "R", "in": "1", "result": "Groundout", "evo": "67.5", "la": "-9", "dist": "14", "is_hh": false, "is_brl": false, "pitcher": "zack littell", "pitch": "SL", "pitcherLR": "R"}, {"created_at": "2025-08-29 18:45:38", "player": "ivan herrera", "game": "stl @ cin", "hr/park": "21/30", "pa": "2", "dt": "2025-08-29", "team": "stl", "stadium": "cin", "bats": "R", "in": "1", "result": "Home Run", "evo": "104.8", "la": "24", "dist": "395", "is_hh": true, "is_brl": true, "pitcher": "zack littell", "pitch": "FF", "pitcherLR": "R"}, {"created_at": "2025-08-29 18:45:38", "player": "lars nootbaar", "game": "stl @ cin", "hr/park": "", "pa": "1", "dt": "2025-08-29", "team": "stl", "stadium": "cin", "bats": "L", "in": "1", "result": "Groundout", "evo": "73.9", "la": "-10", "dist": "15", "is_hh": false, "is_brl": false, "pitcher": "zack littell", "pitch": "FS", "pitcherLR": "R"}], "tb @ wsh": [{"created_at": "2025-08-29 18:47:07", "player": "chandler simpson", "game": "tb @ wsh", "hr/park": "", "pa": "1", "dt": "2025-08-29", "team": "tb", "stadium": "wsh", "bats": "L", "in": "1", "result": "Batter Timeout", "evo": "", "la": "", "dist": "", "is_hh": false, "is_brl": false}], "atl @ phi": [], "mil @ tor": [], "pit @ bos": [], "sea @ cle": [], "mia @ nym": [], "nyy @ chw": [], "laa @ hou": [], "det @ kc": [], "sd @ min": [], "chc @ col": [], "tex @ ath": [], "ari @ lad": [], "bal @ sf": []}