{
  "ath @ min": {
    "81": {
      "player": "mickey gasper",
      "pitcher": "osvaldo bido",
      "result": "In play, out(s)",
      "pitch": "Slider"
    },
    "80": {
      "player": "austin martin",
      "pitcher": "osvaldo bido",
      "result": "Swinging Strike",
      "pitch": "Slider"
    },
    "79": {
      "player": "james outman",
      "pitcher": "osvaldo bido",
      "result": "Swinging Strike",
      "pitch": "Slider"
    },
    "78": {
      "player": "royce lewis",
      "pitcher": "osvaldo bido",
      "result": "In play, run(s)",
      "pitch": "Slider"
    },
    "77": {
      "player": "kody clemens",
      "pitcher": "osvaldo bido",
      "result": "In play, no out",
      "pitch": "Changeup"
    },
    "76": {
      "player": "max schuemann",
      "pitcher": "brooks kriske",
      "result": "Called Strike",
      "pitch": "Splitter"
    },
    "75": {
      "player": "brett harris",
      "pitcher": "brooks kriske",
      "result": "In play, out(s)",
      "pitch": "4-Seam Fastball"
    },
    "74": {
      "player": "willie maciver",
      "pitcher": "brooks kriske",
      "result": "In play, out(s)",
      "pitch": "Splitter"
    },
    "73": {
      "player": "luke keaschall",
      "pitcher": "osvaldo bido",
      "result": "In play, out(s)",
      "pitch": "Sinker"
    },
    "72": {
      "player": "brooks lee",
      "pitcher": "osvaldo bido",
      "result": "Called Strike",
      "pitch": "Slider"
    },
    "71": {
      "player": "trevor larnach",
      "pitcher": "osvaldo bido",
      "result": "In play, out(s)",
      "pitch": "4-Seam Fastball"
    },
    "70": {
      "player": "carlos cortes",
      "pitcher": "erasmo ramirez",
      "result": "In play, out(s)",
      "pitch": "Sinker"
    },
    "69": {
      "player": "darell hernaiz",
      "pitcher": "erasmo ramirez",
      "result": "In play, out(s)",
      "pitch": "Curveball"
    },
    "68": {
      "player": "tyler soderstrom",
      "pitcher": "erasmo ramirez",
      "result": "In play, no out",
      "pitch": "Cutter"
    },
    "67": {
      "player": "brent rooker",
      "pitcher": "erasmo ramirez",
      "result": "In play, out(s)",
      "pitch": "Sinker"
    },
    "66": {
      "player": "byron buxton",
      "pitcher": "osvaldo bido",
      "result": "In play, out(s)",
      "pitch": "Sinker"
    },
    "65": {
      "player": "mickey gasper",
      "pitcher": "osvaldo bido",
      "result": "In play, out(s)",
      "pitch": "Changeup"
    },
    "64": {
      "player": "austin martin",
      "pitcher": "osvaldo bido",
      "result": "Swinging Strike",
      "pitch": "Slider"
    },
    "63": {
      "player": "lawrence butler",
      "pitcher": "erasmo ramirez",
      "result": "In play, out(s)",
      "pitch": "4-Seam Fastball"
    },
    "62": {
      "player": "nick kurtz",
      "pitcher": "erasmo ramirez",
      "result": "In play, no out",
      "pitch": "Cutter"
    },
    "61": {
      "player": "max schuemann",
      "pitcher": "michael tonkin",
      "result": "In play, run(s)",
      "pitch": "4-Seam Fastball"
    },
    "60": {
      "player": "brett harris",
      "pitcher": "michael tonkin",
      "result": "In play, out(s)",
      "pitch": "4-Seam Fastball"
    },
    "59": {
      "player": "willie maciver",
      "pitcher": "michael tonkin",
      "result": "Ball",
      "pitch": "4-Seam Fastball"
    },
    "58": {
      "player": "carlos cortes",
      "pitcher": "michael tonkin",
      "result": "Called Strike",
      "pitch": "Slider"
    },
    "57": {
      "player": "james outman",
      "pitcher": "ben bowden",
      "result": "Swinging Strike",
      "pitch": "Slider"
    },
    "56": {
      "player": "royce lewis",
      "pitcher": "ben bowden",
      "result": "In play, out(s)",
      "pitch": "4-Seam Fastball"
    },
    "55": {
      "player": "kody clemens",
      "pitcher": "ben bowden",
      "result": "Swinging Strike",
      "pitch": "4-Seam Fastball"
    },
    "54": {
      "player": "darell hernaiz",
      "pitcher": "michael tonkin",
      "result": "In play, out(s)",
      "pitch": "Slider"
    },
    "53": {
      "player": "tyler soderstrom",
      "pitcher": "michael tonkin",
      "result": "In play, no out",
      "pitch": "4-Seam Fastball"
    },
    "52": {
      "player": "brent rooker",
      "pitcher": "michael tonkin",
      "result": "In play, out(s)",
      "pitch": "4-Seam Fastball"
    },
    "51": {
      "player": "lawrence butler",
      "pitcher": "michael tonkin",
      "result": "Called Strike",
      "pitch": "4-Seam Fastball"
    },
    "50": {
      "player": "nick kurtz",
      "pitcher": "michael tonkin",
      "result": "In play, run(s)",
      "pitch": "Sinker"
    },
    "49": {
      "player": "luke keaschall",
      "pitcher": "jack perkins",
      "result": "In play, out(s)",
      "pitch": "4-Seam Fastball"
    },
    "48": {
      "player": "brooks lee",
      "pitcher": "jack perkins",
      "result": "Ball",
      "pitch": "4-Seam Fastball"
    },
    "47": {
      "player": "trevor larnach",
      "pitcher": "jack perkins",
      "result": "In play, out(s)",
      "pitch": "4-Seam Fastball"
    },
    "46": {
      "player": "byron buxton",
      "pitcher": "jack perkins",
      "result": "In play, out(s)",
      "pitch": "Sweeper"
    },
    "45": {
      "player": "mickey gasper",
      "pitcher": "jack perkins",
      "result": "Hit By Pitch",
      "pitch": "Cutter"
    },
    "44": {
      "player": "max schuemann",
      "pitcher": "jose urena",
      "result": "Swinging Strike",
      "pitch": "Slider"
    },
    "43": {
      "player": "brett harris",
      "pitcher": "jose urena",
      "result": "Hit By Pitch",
      "pitch": "4-Seam Fastball"
    },
    "42": {
      "player": "willie maciver",
      "pitcher": "jose urena",
      "result": "In play, out(s)",
      "pitch": "Slider"
    },
    "41": {
      "player": "carlos cortes",
      "pitcher": "jose urena",
      "result": "In play, out(s)",
      "pitch": "Slider"
    },
    "40": {
      "player": "austin martin",
      "pitcher": "jack perkins",
      "result": "In play, run(s)",
      "pitch": "Sweeper"
    },
    "39": {
      "player": "james outman",
      "pitcher": "jack perkins",
      "result": "In play, run(s)",
      "pitch": "Changeup"
    },
    "38": {
      "player": "royce lewis",
      "pitcher": "jack perkins",
      "result": "In play, out(s)",
      "pitch": "Sweeper"
    },
    "37": {
      "player": "kody clemens",
      "pitcher": "jack perkins",
      "result": "In play, out(s)",
      "pitch": "4-Seam Fastball"
    },
    "36": {
      "player": "luke keaschall",
      "pitcher": "jack perkins",
      "result": "Ball",
      "pitch": "4-Seam Fastball"
    },
    "35": {
      "player": "brooks lee",
      "pitcher": "jack perkins",
      "result": "Ball",
      "pitch": "Sweeper"
    },
    "34": {
      "player": "trevor larnach",
      "pitcher": "jack perkins",
      "result": "In play, no out",
      "pitch": "4-Seam Fastball"
    },
    "33": {
      "player": "darell hernaiz",
      "pitcher": "jose urena",
      "result": "In play, out(s)",
      "pitch": "4-Seam Fastball"
    },
    "32": {
      "player": "tyler soderstrom",
      "pitcher": "jose urena",
      "result": "In play, no out",
      "pitch": "Changeup"
    },
    "31": {
      "player": "brent rooker",
      "pitcher": "jose urena",
      "result": "In play, out(s)",
      "pitch": "4-Seam Fastball"
    },
    "30": {
      "player": "lawrence butler",
      "pitcher": "jose urena",
      "result": "In play, out(s)",
      "pitch": "Slider"
    },
    "29": {
      "player": "byron buxton",
      "pitcher": "jack perkins",
      "result": "In play, out(s)",
      "pitch": "Cutter"
    },
    "28": {
      "player": "mickey gasper",
      "pitcher": "jack perkins",
      "result": "In play, out(s)",
      "pitch": "4-Seam Fastball"
    },
    "27": {
      "player": "austin martin",
      "pitcher": "jack perkins",
      "result": "Ball",
      "pitch": "4-Seam Fastball"
    },
    "26": {
      "player": "james outman",
      "pitcher": "jack perkins",
      "result": "Swinging Strike",
      "pitch": "4-Seam Fastball"
    },
    "25": {
      "player": "nick kurtz",
      "pitcher": "jose urena",
      "result": "In play, out(s)",
      "pitch": "4-Seam Fastball"
    },
    "24": {
      "player": "max schuemann",
      "pitcher": "jose urena",
      "result": "In play, out(s)",
      "pitch": "Sinker"
    },
    "23": {
      "player": "brett harris",
      "pitcher": "jose urena",
      "result": "Swinging Strike",
      "pitch": "Slider"
    },
    "22": {
      "player": "royce lewis",
      "pitcher": "jack perkins",
      "result": "Swinging Strike",
      "pitch": "4-Seam Fastball"
    },
    "21": {
      "player": "kody clemens",
      "pitcher": "jack perkins",
      "result": "In play, out(s)",
      "pitch": "Sweeper"
    },
    "20": {
      "player": "luke keaschall",
      "pitcher": "jack perkins",
      "result": "In play, out(s)",
      "pitch": "Sweeper"
    },
    "19": {
      "player": "willie maciver",
      "pitcher": "jose urena",
      "result": "In play, out(s)",
      "pitch": "4-Seam Fastball"
    },
    "18": {
      "player": "carlos cortes",
      "pitcher": "jose urena",
      "result": "In play, run(s)",
      "pitch": "Changeup"
    },
    "17": {
      "player": "darell hernaiz",
      "pitcher": "jose urena",
      "result": "In play, run(s)",
      "pitch": "Slider"
    },
    "16": {
      "player": "tyler soderstrom",
      "pitcher": "jose urena",
      "result": "Ball",
      "pitch": "4-Seam Fastball"
    },
    "15": {
      "player": "brent rooker",
      "pitcher": "jose urena",
      "result": "In play, run(s)",
      "pitch": "4-Seam Fastball"
    },
    "14": {
      "player": "lawrence butler",
      "pitcher": "jose urena",
      "result": "In play, run(s)",
      "pitch": "Changeup"
    },
    "13": {
      "player": "nick kurtz",
      "pitcher": "jose urena",
      "result": "Ball",
      "pitch": "4-Seam Fastball"
    },
    "12": {
      "player": "max schuemann",
      "pitcher": "jose urena",
      "result": "In play, out(s)",
      "pitch": "Sinker"
    },
    "11": {
      "player": "brett harris",
      "pitcher": "jose urena",
      "result": "In play, no out",
      "pitch": "4-Seam Fastball"
    },
    "10": {
      "player": "willie maciver",
      "pitcher": "jose urena",
      "result": "Hit By Pitch",
      "pitch": "4-Seam Fastball"
    },
    "9": {
      "player": "carlos cortes",
      "pitcher": "jose urena",
      "result": "In play, out(s)",
      "pitch": "Changeup"
    },
    "8": {
      "player": "brooks lee",
      "pitcher": "jack perkins",
      "result": "In play, out(s)",
      "pitch": "Cutter"
    },
    "7": {
      "player": "trevor larnach",
      "pitcher": "jack perkins",
      "result": "In play, out(s)",
      "pitch": "Cutter"
    },
    "6": {
      "player": "byron buxton",
      "pitcher": "jack perkins",
      "result": "In play, out(s)",
      "pitch": "4-Seam Fastball"
    },
    "5": {
      "player": "darell hernaiz",
      "pitcher": "jose urena",
      "result": "In play, out(s)",
      "pitch": "4-Seam Fastball"
    },
    "4": {
      "player": "tyler soderstrom",
      "pitcher": "jose urena",
      "result": "In play, no out",
      "pitch": "4-Seam Fastball"
    },
    "3": {
      "player": "brent rooker",
      "pitcher": "jose urena",
      "result": "In play, out(s)",
      "pitch": "Slider"
    },
    "2": {
      "player": "lawrence butler",
      "pitcher": "jose urena",
      "result": "In play, no out",
      "pitch": "Changeup"
    },
    "1": {
      "player": "nick kurtz",
      "pitcher": "jose urena",
      "result": "Swinging Strike",
      "pitch": "Changeup"
    }
  },
  "tex @ kc": {
    "80": {
      "player": "kyle higashioka",
      "pitcher": "carlos estevez",
      "result": "Swinging Strike",
      "pitch": "Slider"
    },
    "79": {
      "player": "ezequiel duran",
      "pitcher": "carlos estevez",
      "result": "In play, out(s)",
      "pitch": "4-Seam Fastball"
    },
    "78": {
      "player": "corey seager",
      "pitcher": "carlos estevez",
      "result": "In play, out(s)",
      "pitch": "4-Seam Fastball"
    },
    "77": {
      "player": "salvador perez",
      "pitcher": "robert garcia",
      "result": "Swinging Strike",
      "pitch": "Slider"
    },
    "76": {
      "player": "vinnie pasquantino",
      "pitcher": "robert garcia",
      "result": "In play, out(s)",
      "pitch": "Slider"
    },
    "75": {
      "player": "bobby witt",
      "pitcher": "robert garcia",
      "result": "In play, out(s)",
      "pitch": "4-Seam Fastball"
    },
    "74": {
      "player": "maikel garcia",
      "pitcher": "robert garcia",
      "result": "Ball",
      "pitch": "4-Seam Fastball"
    },
    "73": {
      "player": "wyatt langford",
      "pitcher": "taylor clarke",
      "result": "Swinging Strike",
      "pitch": "Sinker"
    },
    "72": {
      "player": "jonah heim",
      "pitcher": "taylor clarke",
      "result": "Swinging Strike",
      "pitch": "Slider"
    },
    "71": {
      "player": "cody freeman",
      "pitcher": "taylor clarke",
      "result": "In play, out(s)",
      "pitch": "Sinker"
    },
    "70": {
      "player": "mike yastrzemski",
      "pitcher": "danny coulombe",
      "result": "In play, out(s)",
      "pitch": "Sweeper"
    },
    "69": {
      "player": "luke maile",
      "pitcher": "danny coulombe",
      "result": "Ball",
      "pitch": "4-Seam Fastball"
    },
    "68": {
      "player": "nick loftin",
      "pitcher": "danny coulombe",
      "result": "In play, out(s)",
      "pitch": "Cutter"
    },
    "67": {
      "player": "jonathan india",
      "pitcher": "luis curvelo",
      "result": "Ball",
      "pitch": "Sinker"
    },
    "66": {
      "player": "kyle isbel",
      "pitcher": "luis curvelo",
      "result": "Ball",
      "pitch": "4-Seam Fastball"
    },
    "65": {
      "player": "salvador perez",
      "pitcher": "luis curvelo",
      "result": "In play, no out",
      "pitch": "Sinker"
    },
    "64": {
      "player": "vinnie pasquantino",
      "pitcher": "luis curvelo",
      "result": "Swinging Strike",
      "pitch": "Slider"
    },
    "63": {
      "player": "josh smith",
      "pitcher": "john schreiber",
      "result": "In play, out(s)",
      "pitch": "Cutter"
    },
    "62": {
      "player": "josh jung",
      "pitcher": "john schreiber",
      "result": "Swinging Strike",
      "pitch": "Sinker"
    },
    "61": {
      "player": "evan carter",
      "pitcher": "daniel lynch",
      "result": "Hit By Pitch",
      "pitch": "Sinker"
    },
    "60": {
      "player": "kyle higashioka",
      "pitcher": "daniel lynch",
      "result": "Swinging Strike",
      "pitch": "Slider"
    },
    "59": {
      "player": "ezequiel duran",
      "pitcher": "daniel lynch",
      "result": "In play, no out",
      "pitch": "Knuckle Curve"
    },
    "58": {
      "player": "bobby witt",
      "pitcher": "luis curvelo",
      "result": "In play, out(s)",
      "pitch": "Sinker"
    },
    "57": {
      "player": "maikel garcia",
      "pitcher": "luis curvelo",
      "result": "Called Strike",
      "pitch": "Sinker"
    },
    "56": {
      "player": "mike yastrzemski",
      "pitcher": "luis curvelo",
      "result": "Ball",
      "pitch": "Sinker"
    },
    "55": {
      "player": "luke maile",
      "pitcher": "luis curvelo",
      "result": "Called Strike",
      "pitch": "4-Seam Fastball"
    },
    "54": {
      "player": "corey seager",
      "pitcher": "angel zerpa",
      "result": "Swinging Strike",
      "pitch": "Slider"
    },
    "53": {
      "player": "wyatt langford",
      "pitcher": "angel zerpa",
      "result": "In play, out(s)",
      "pitch": "Slider"
    },
    "52": {
      "player": "jonah heim",
      "pitcher": "angel zerpa",
      "result": "In play, out(s)",
      "pitch": "Slider"
    },
    "51": {
      "player": "nick loftin",
      "pitcher": "jacob webb",
      "result": "In play, out(s)",
      "pitch": "Changeup"
    },
    "50": {
      "player": "jonathan india",
      "pitcher": "jacob webb",
      "result": "Ball",
      "pitch": "4-Seam Fastball"
    },
    "49": {
      "player": "randal grichuk",
      "pitcher": "jacob webb",
      "result": "In play, out(s)",
      "pitch": "4-Seam Fastball"
    },
    "48": {
      "player": "salvador perez",
      "pitcher": "jacob webb",
      "result": "In play, out(s)",
      "pitch": "4-Seam Fastball"
    },
    "47": {
      "player": "vinnie pasquantino",
      "pitcher": "jacob webb",
      "result": "In play, run(s)",
      "pitch": "Changeup"
    },
    "46": {
      "player": "cody freeman",
      "pitcher": "angel zerpa",
      "result": "In play, out(s)",
      "pitch": "Sinker"
    },
    "45": {
      "player": "josh smith",
      "pitcher": "michael lorenzen",
      "result": "In play, run(s)",
      "pitch": "Sinker"
    },
    "44": {
      "player": "rowdy tellez",
      "pitcher": "michael lorenzen",
      "result": "In play, no out",
      "pitch": "Sinker"
    },
    "43": {
      "player": "evan carter",
      "pitcher": "michael lorenzen",
      "result": "In play, no out",
      "pitch": "Sweeper"
    },
    "42": {
      "player": "joc pederson",
      "pitcher": "michael lorenzen",
      "result": "Swinging Strike",
      "pitch": "Slider"
    },
    "41": {
      "player": "ezequiel duran",
      "pitcher": "michael lorenzen",
      "result": "In play, no out",
      "pitch": "Sinker"
    },
    "40": {
      "player": "corey seager",
      "pitcher": "michael lorenzen",
      "result": "In play, no out",
      "pitch": "Slider"
    },
    "39": {
      "player": "bobby witt",
      "pitcher": "jacob webb",
      "result": "In play, out(s)",
      "pitch": "Sweeper"
    },
    "38": {
      "player": "maikel garcia",
      "pitcher": "patrick corbin",
      "result": "In play, run(s)",
      "pitch": "Sinker"
    },
    "37": {
      "player": "tyler tolbert",
      "pitcher": "patrick corbin",
      "result": "In play, run(s)",
      "pitch": "Cutter"
    },
    "36": {
      "player": "luke maile",
      "pitcher": "patrick corbin",
      "result": "In play, out(s)",
      "pitch": "Slider"
    },
    "35": {
      "player": "nick loftin",
      "pitcher": "patrick corbin",
      "result": "Ball",
      "pitch": "Cutter"
    },
    "34": {
      "player": "jonathan india",
      "pitcher": "patrick corbin",
      "result": "In play, no out",
      "pitch": "Slider"
    },
    "33": {
      "player": "wyatt langford",
      "pitcher": "michael lorenzen",
      "result": "In play, out(s)",
      "pitch": "Sinker"
    },
    "32": {
      "player": "jonah heim",
      "pitcher": "michael lorenzen",
      "result": "In play, no out",
      "pitch": "4-Seam Fastball"
    },
    "31": {
      "player": "cody freeman",
      "pitcher": "michael lorenzen",
      "result": "In play, no out",
      "pitch": "4-Seam Fastball"
    },
    "30": {
      "player": "josh smith",
      "pitcher": "michael lorenzen",
      "result": "In play, out(s)",
      "pitch": "Sinker"
    },
    "29": {
      "player": "rowdy tellez",
      "pitcher": "michael lorenzen",
      "result": "Swinging Strike",
      "pitch": "Curveball"
    },
    "28": {
      "player": "randal grichuk",
      "pitcher": "patrick corbin",
      "result": "In play, out(s)",
      "pitch": "Slider"
    },
    "27": {
      "player": "salvador perez",
      "pitcher": "patrick corbin",
      "result": "In play, run(s)",
      "pitch": "Cutter"
    },
    "26": {
      "player": "vinnie pasquantino",
      "pitcher": "patrick corbin",
      "result": "In play, out(s)",
      "pitch": "Cutter"
    },
    "25": {
      "player": "bobby witt",
      "pitcher": "patrick corbin",
      "result": "In play, no out",
      "pitch": "Slider"
    },
    "24": {
      "player": "maikel garcia",
      "pitcher": "patrick corbin",
      "result": "In play, out(s)",
      "pitch": "Cutter"
    },
    "23": {
      "player": "evan carter",
      "pitcher": "michael lorenzen",
      "result": "In play, out(s)",
      "pitch": "Changeup"
    },
    "22": {
      "player": "joc pederson",
      "pitcher": "michael lorenzen",
      "result": "In play, run(s)",
      "pitch": "Curveball"
    },
    "21": {
      "player": "ezequiel duran",
      "pitcher": "michael lorenzen",
      "result": "In play, out(s)",
      "pitch": "Slider"
    },
    "20": {
      "player": "corey seager",
      "pitcher": "michael lorenzen",
      "result": "In play, no out",
      "pitch": "Cutter"
    },
    "19": {
      "player": "wyatt langford",
      "pitcher": "michael lorenzen",
      "result": "Ball",
      "pitch": "Sinker"
    },
    "18": {
      "player": "jonah heim",
      "pitcher": "michael lorenzen",
      "result": "In play, out(s)",
      "pitch": "4-Seam Fastball"
    },
    "17": {
      "player": "tyler tolbert",
      "pitcher": "patrick corbin",
      "result": "In play, out(s)",
      "pitch": "Sinker"
    },
    "16": {
      "player": "luke maile",
      "pitcher": "patrick corbin",
      "result": "Called Strike",
      "pitch": "Sinker"
    },
    "15": {
      "player": "nick loftin",
      "pitcher": "patrick corbin",
      "result": "In play, run(s)",
      "pitch": "Slider"
    },
    "14": {
      "player": "jonathan india",
      "pitcher": "patrick corbin",
      "result": "In play, out(s)",
      "pitch": "4-Seam Fastball"
    },
    "13": {
      "player": "cody freeman",
      "pitcher": "michael lorenzen",
      "result": "Swinging Strike",
      "pitch": "Slider"
    },
    "12": {
      "player": "josh smith",
      "pitcher": "michael lorenzen",
      "result": "In play, out(s)",
      "pitch": "Sinker"
    },
    "11": {
      "player": "rowdy tellez",
      "pitcher": "michael lorenzen",
      "result": "Swinging Strike",
      "pitch": "Slider"
    },
    "10": {
      "player": "evan carter",
      "pitcher": "michael lorenzen",
      "result": "Hit By Pitch",
      "pitch": "Curveball"
    },
    "9": {
      "player": "randal grichuk",
      "pitcher": "patrick corbin",
      "result": "In play, out(s)",
      "pitch": "4-Seam Fastball"
    },
    "8": {
      "player": "salvador perez",
      "pitcher": "patrick corbin",
      "result": "Ball",
      "pitch": "Sinker"
    },
    "7": {
      "player": "vinnie pasquantino",
      "pitcher": "patrick corbin",
      "result": "Swinging Strike",
      "pitch": "Slider"
    },
    "6": {
      "player": "bobby witt",
      "pitcher": "patrick corbin",
      "result": "In play, no out",
      "pitch": "Changeup"
    },
    "5": {
      "player": "maikel garcia",
      "pitcher": "patrick corbin",
      "result": "In play, out(s)",
      "pitch": "Cutter"
    },
    "4": {
      "player": "joc pederson",
      "pitcher": "michael lorenzen",
      "result": "Swinging Strike",
      "pitch": "Changeup"
    },
    "3": {
      "player": "marcus semien",
      "pitcher": "michael lorenzen",
      "result": "Swinging Strike",
      "pitch": "Slider"
    },
    "2": {
      "player": "corey seager",
      "pitcher": "michael lorenzen",
      "result": "In play, no out",
      "pitch": "4-Seam Fastball"
    },
    "1": {
      "player": "wyatt langford",
      "pitcher": "michael lorenzen",
      "result": "In play, out(s)",
      "pitch": "Sinker"
    }
  },
  "mil @ chc": {
    "74": {
      "player": "seiya suzuki",
      "pitcher": "trevor megill",
      "result": "In play, out(s)",
      "pitch": "Knuckle Curve"
    },
    "73": {
      "player": "kyle tucker",
      "pitcher": "trevor megill",
      "result": "In play, out(s)",
      "pitch": "4-Seam Fastball"
    },
    "72": {
      "player": "michael busch",
      "pitcher": "trevor megill",
      "result": "Swinging Strike",
      "pitch": "Knuckle Curve"
    },
    "71": {
      "player": "carson kelly",
      "pitcher": "trevor megill",
      "result": "In play, no out",
      "pitch": "4-Seam Fastball"
    },
    "70": {
      "player": "blake perkins",
      "pitcher": "drew pomeranz",
      "result": "Swinging Strike",
      "pitch": "4-Seam Fastball"
    },
    "69": {
      "player": "brice turang",
      "pitcher": "drew pomeranz",
      "result": "In play, no out",
      "pitch": "4-Seam Fastball"
    },
    "68": {
      "player": "caleb durbin",
      "pitcher": "drew pomeranz",
      "result": "In play, out(s)",
      "pitch": "4-Seam Fastball"
    },
    "67": {
      "player": "andrew vaughn",
      "pitcher": "drew pomeranz",
      "result": "In play, out(s)",
      "pitch": "Knuckle Curve"
    },
    "66": {
      "player": "owen caissie",
      "pitcher": "abner uribe",
      "result": "In play, out(s)",
      "pitch": "Sinker"
    },
    "65": {
      "player": "willi castro",
      "pitcher": "abner uribe",
      "result": "In play, out(s)",
      "pitch": "Sinker"
    },
    "64": {
      "player": "nico hoerner",
      "pitcher": "abner uribe",
      "result": "Swinging Strike",
      "pitch": "Slider"
    },
    "63": {
      "player": "ian happ",
      "pitcher": "abner uribe",
      "result": "Ball",
      "pitch": "Sinker"
    },
    "62": {
      "player": "pete crow armstrong",
      "pitcher": "abner uribe",
      "result": "Ball",
      "pitch": "Slider"
    },
    "61": {
      "player": "christian yelich",
      "pitcher": "ryan brasier",
      "result": "In play, out(s)",
      "pitch": "4-Seam Fastball"
    },
    "60": {
      "player": "william contreras",
      "pitcher": "ryan brasier",
      "result": "Ball",
      "pitch": "4-Seam Fastball"
    },
    "59": {
      "player": "isaac collins",
      "pitcher": "ryan brasier",
      "result": "In play, run(s)",
      "pitch": "Slider"
    },
    "58": {
      "player": "sal frelick",
      "pitcher": "ryan brasier",
      "result": "In play, no out",
      "pitch": "Cutter"
    },
    "57": {
      "player": "andruw monasterio",
      "pitcher": "ryan brasier",
      "result": "In play, no out",
      "pitch": "Slider"
    },
    "56": {
      "player": "blake perkins",
      "pitcher": "ryan brasier",
      "result": "Swinging Strike",
      "pitch": "Slider"
    },
    "55": {
      "player": "seiya suzuki",
      "pitcher": "jared koenig",
      "result": "Called Strike",
      "pitch": "Sinker"
    },
    "54": {
      "player": "kyle tucker",
      "pitcher": "jared koenig",
      "result": "In play, out(s)",
      "pitch": "Cutter"
    },
    "53": {
      "player": "michael busch",
      "pitcher": "jared koenig",
      "result": "Ball",
      "pitch": "Sinker"
    },
    "52": {
      "player": "brice turang",
      "pitcher": "shota imanaga",
      "result": "In play, out(s)",
      "pitch": "Sweeper"
    },
    "51": {
      "player": "caleb durbin",
      "pitcher": "shota imanaga",
      "result": "In play, out(s)",
      "pitch": "4-Seam Fastball"
    },
    "50": {
      "player": "andrew vaughn",
      "pitcher": "shota imanaga",
      "result": "Ball",
      "pitch": "Sweeper"
    },
    "49": {
      "player": "christian yelich",
      "pitcher": "shota imanaga",
      "result": "Called Strike",
      "pitch": "4-Seam Fastball"
    },
    "48": {
      "player": "reese mcguire",
      "pitcher": "grant anderson",
      "result": "Swinging Strike",
      "pitch": "4-Seam Fastball"
    },
    "47": {
      "player": "dansby swanson",
      "pitcher": "grant anderson",
      "result": "In play, out(s)",
      "pitch": "4-Seam Fastball"
    },
    "46": {
      "player": "willi castro",
      "pitcher": "grant anderson",
      "result": "In play, out(s)",
      "pitch": "Sweeper"
    },
    "45": {
      "player": "nico hoerner",
      "pitcher": "grant anderson",
      "result": "In play, no out",
      "pitch": "Sinker"
    },
    "44": {
      "player": "william contreras",
      "pitcher": "shota imanaga",
      "result": "In play, out(s)",
      "pitch": "Sweeper"
    },
    "43": {
      "player": "isaac collins",
      "pitcher": "shota imanaga",
      "result": "In play, out(s)",
      "pitch": "4-Seam Fastball"
    },
    "42": {
      "player": "sal frelick",
      "pitcher": "shota imanaga",
      "result": "In play, out(s)",
      "pitch": "4-Seam Fastball"
    },
    "41": {
      "player": "ian happ",
      "pitcher": "nick mears",
      "result": "In play, out(s)",
      "pitch": "4-Seam Fastball"
    },
    "40": {
      "player": "pete crow armstrong",
      "pitcher": "nick mears",
      "result": "In play, run(s)",
      "pitch": "4-Seam Fastball"
    },
    "39": {
      "player": "seiya suzuki",
      "pitcher": "quinn priester",
      "result": "Ball",
      "pitch": "Slider"
    },
    "38": {
      "player": "kyle tucker",
      "pitcher": "quinn priester",
      "result": "In play, out(s)",
      "pitch": "Sinker"
    },
    "37": {
      "player": "michael busch",
      "pitcher": "quinn priester",
      "result": "In play, no out",
      "pitch": "Cutter"
    },
    "36": {
      "player": "reese mcguire",
      "pitcher": "quinn priester",
      "result": "Ball",
      "pitch": "Slider"
    },
    "35": {
      "player": "joey ortiz",
      "pitcher": "shota imanaga",
      "result": "In play, out(s)",
      "pitch": "Splitter"
    },
    "34": {
      "player": "brandon lockridge",
      "pitcher": "shota imanaga",
      "result": "In play, out(s)",
      "pitch": "Sweeper"
    },
    "33": {
      "player": "brice turang",
      "pitcher": "shota imanaga",
      "result": "Swinging Strike",
      "pitch": "Sweeper"
    },
    "32": {
      "player": "dansby swanson",
      "pitcher": "quinn priester",
      "result": "In play, out(s)",
      "pitch": "Sinker"
    },
    "31": {
      "player": "willi castro",
      "pitcher": "quinn priester",
      "result": "Hit By Pitch",
      "pitch": "Cutter"
    },
    "30": {
      "player": "nico hoerner",
      "pitcher": "quinn priester",
      "result": "Swinging Strike",
      "pitch": "Slider"
    },
    "29": {
      "player": "ian happ",
      "pitcher": "quinn priester",
      "result": "Ball",
      "pitch": "Sinker"
    },
    "28": {
      "player": "pete crow armstrong",
      "pitcher": "quinn priester",
      "result": "Swinging Strike",
      "pitch": "Cutter"
    },
    "27": {
      "player": "caleb durbin",
      "pitcher": "shota imanaga",
      "result": "In play, out(s)",
      "pitch": "4-Seam Fastball"
    },
    "26": {
      "player": "andrew vaughn",
      "pitcher": "shota imanaga",
      "result": "In play, out(s)",
      "pitch": "Splitter"
    },
    "25": {
      "player": "christian yelich",
      "pitcher": "shota imanaga",
      "result": "Swinging Strike",
      "pitch": "Sweeper"
    },
    "24": {
      "player": "seiya suzuki",
      "pitcher": "quinn priester",
      "result": "In play, out(s)",
      "pitch": "Slider"
    },
    "23": {
      "player": "kyle tucker",
      "pitcher": "quinn priester",
      "result": "In play, out(s)",
      "pitch": "Sinker"
    },
    "22": {
      "player": "michael busch",
      "pitcher": "quinn priester",
      "result": "Swinging Strike",
      "pitch": "Slider"
    },
    "21": {
      "player": "william contreras",
      "pitcher": "shota imanaga",
      "result": "Swinging Strike",
      "pitch": "4-Seam Fastball"
    },
    "20": {
      "player": "isaac collins",
      "pitcher": "shota imanaga",
      "result": "In play, out(s)",
      "pitch": "4-Seam Fastball"
    },
    "19": {
      "player": "sal frelick",
      "pitcher": "shota imanaga",
      "result": "In play, out(s)",
      "pitch": "4-Seam Fastball"
    },
    "18": {
      "player": "joey ortiz",
      "pitcher": "shota imanaga",
      "result": "In play, no out",
      "pitch": "4-Seam Fastball"
    },
    "17": {
      "player": "reese mcguire",
      "pitcher": "quinn priester",
      "result": "In play, out(s)",
      "pitch": "Sinker"
    },
    "16": {
      "player": "dansby swanson",
      "pitcher": "quinn priester",
      "result": "Ball",
      "pitch": "Cutter"
    },
    "15": {
      "player": "willi castro",
      "pitcher": "quinn priester",
      "result": "In play, no out",
      "pitch": "Sinker"
    },
    "14": {
      "player": "nico hoerner",
      "pitcher": "quinn priester",
      "result": "In play, out(s)",
      "pitch": "Sinker"
    },
    "13": {
      "player": "ian happ",
      "pitcher": "quinn priester",
      "result": "In play, no out",
      "pitch": "Sinker"
    },
    "12": {
      "player": "pete crow armstrong",
      "pitcher": "quinn priester",
      "result": "In play, out(s)",
      "pitch": "Slider"
    },
    "11": {
      "player": "brandon lockridge",
      "pitcher": "shota imanaga",
      "result": "In play, out(s)",
      "pitch": "Splitter"
    },
    "10": {
      "player": "brice turang",
      "pitcher": "shota imanaga",
      "result": "In play, run(s)",
      "pitch": "4-Seam Fastball"
    },
    "9": {
      "player": "caleb durbin",
      "pitcher": "shota imanaga",
      "result": "Swinging Strike",
      "pitch": "Splitter"
    },
    "8": {
      "player": "andrew vaughn",
      "pitcher": "shota imanaga",
      "result": "In play, out(s)",
      "pitch": "4-Seam Fastball"
    },
    "7": {
      "player": "christian yelich",
      "pitcher": "shota imanaga",
      "result": "Ball",
      "pitch": "4-Seam Fastball"
    },
    "6": {
      "player": "seiya suzuki",
      "pitcher": "quinn priester",
      "result": "In play, out(s)",
      "pitch": "Sinker"
    },
    "5": {
      "player": "kyle tucker",
      "pitcher": "quinn priester",
      "result": "Ball",
      "pitch": "Slider"
    },
    "4": {
      "player": "michael busch",
      "pitcher": "quinn priester",
      "result": "Swinging Strike",
      "pitch": "Cutter"
    },
    "3": {
      "player": "william contreras",
      "pitcher": "shota imanaga",
      "result": "In play, out(s)",
      "pitch": "Sweeper"
    },
    "2": {
      "player": "isaac collins",
      "pitcher": "shota imanaga",
      "result": "In play, out(s)",
      "pitch": "4-Seam Fastball"
    },
    "1": {
      "player": "sal frelick",
      "pitcher": "shota imanaga",
      "result": "In play, no out",
      "pitch": "4-Seam Fastball"
    }
  },
  "lad @ col": {
    "83": {
      "player": "ezequiel tovar",
      "pitcher": "alex vesia",
      "result": "Ball",
      "pitch": "4-Seam Fastball"
    },
    "82": {
      "player": "tyler freeman",
      "pitcher": "alex vesia",
      "result": "In play, out(s)",
      "pitch": "Changeup"
    },
    "81": {
      "player": "ryan ritter",
      "pitcher": "alex vesia",
      "result": "In play, no out",
      "pitch": "4-Seam Fastball"
    },
    "80": {
      "player": "orlando arcia",
      "pitcher": "alex vesia",
      "result": "Swinging Strike",
      "pitch": "Slider"
    },
    "79": {
      "player": "alex call",
      "pitcher": "juan mejia",
      "result": "In play, out(s)",
      "pitch": "4-Seam Fastball"
    },
    "78": {
      "player": "andy pages",
      "pitcher": "juan mejia",
      "result": "Swinging Strike",
      "pitch": "4-Seam Fastball"
    },
    "77": {
      "player": "dalton rushing",
      "pitcher": "juan mejia",
      "result": "In play, out(s)",
      "pitch": "4-Seam Fastball"
    },
    "76": {
      "player": "alex freeland",
      "pitcher": "juan mejia",
      "result": "In play, no out",
      "pitch": "4-Seam Fastball"
    },
    "75": {
      "player": "kyle farmer",
      "pitcher": "matt sauer",
      "result": "In play, out(s)",
      "pitch": "Cutter"
    },
    "74": {
      "player": "braxton fulford",
      "pitcher": "matt sauer",
      "result": "Swinging Strike",
      "pitch": "Cutter"
    },
    "73": {
      "player": "brenton doyle",
      "pitcher": "matt sauer",
      "result": "In play, run(s)",
      "pitch": "Splitter"
    },
    "72": {
      "player": "jordan beck",
      "pitcher": "matt sauer",
      "result": "In play, out(s)",
      "pitch": "Splitter"
    },
    "71": {
      "player": "yanquiel fernandez",
      "pitcher": "matt sauer",
      "result": "In play, no out",
      "pitch": "Cutter"
    },
    "70": {
      "player": "michael conforto",
      "pitcher": "luis peralta",
      "result": "Foul Tip",
      "pitch": "Curveball"
    },
    "69": {
      "player": "will smith",
      "pitcher": "luis peralta",
      "result": "In play, run(s)",
      "pitch": "4-Seam Fastball"
    },
    "68": {
      "player": "freddie freeman",
      "pitcher": "luis peralta",
      "result": "In play, out(s)",
      "pitch": "Curveball"
    },
    "67": {
      "player": "mookie betts",
      "pitcher": "dugan darnell",
      "result": "Ball",
      "pitch": "4-Seam Fastball"
    },
    "66": {
      "player": "miguel rojas",
      "pitcher": "dugan darnell",
      "result": "Ball",
      "pitch": "4-Seam Fastball"
    },
    "65": {
      "player": "alex call",
      "pitcher": "dugan darnell",
      "result": "In play, out(s)",
      "pitch": "Slider"
    },
    "64": {
      "player": "ezequiel tovar",
      "pitcher": "matt sauer",
      "result": "In play, out(s)",
      "pitch": "4-Seam Fastball"
    },
    "63": {
      "player": "tyler freeman",
      "pitcher": "matt sauer",
      "result": "In play, out(s)",
      "pitch": "4-Seam Fastball"
    },
    "62": {
      "player": "ryan ritter",
      "pitcher": "matt sauer",
      "result": "Swinging Strike",
      "pitch": "4-Seam Fastball"
    },
    "61": {
      "player": "orlando arcia",
      "pitcher": "matt sauer",
      "result": "In play, no out",
      "pitch": "4-Seam Fastball"
    },
    "60": {
      "player": "alex call",
      "pitcher": "dugan darnell",
      "result": "Ball In Dirt",
      "pitch": "Slider"
    },
    "59": {
      "player": "andy pages",
      "pitcher": "dugan darnell",
      "result": "Ball",
      "pitch": "4-Seam Fastball"
    },
    "58": {
      "player": "dalton rushing",
      "pitcher": "dugan darnell",
      "result": "In play, out(s)",
      "pitch": "4-Seam Fastball"
    },
    "57": {
      "player": "alex freeland",
      "pitcher": "dugan darnell",
      "result": "In play, out(s)",
      "pitch": "4-Seam Fastball"
    },
    "56": {
      "player": "kyle farmer",
      "pitcher": "ben casparius",
      "result": "In play, out(s)",
      "pitch": "Sweeper"
    },
    "55": {
      "player": "braxton fulford",
      "pitcher": "ben casparius",
      "result": "Ball",
      "pitch": "4-Seam Fastball"
    },
    "54": {
      "player": "brenton doyle",
      "pitcher": "clayton kershaw",
      "result": "In play, run(s)",
      "pitch": "Slider"
    },
    "53": {
      "player": "jordan beck",
      "pitcher": "clayton kershaw",
      "result": "In play, no out",
      "pitch": "4-Seam Fastball"
    },
    "52": {
      "player": "hunter goodman",
      "pitcher": "clayton kershaw",
      "result": "Ball In Dirt",
      "pitch": "Slider"
    },
    "51": {
      "player": "ezequiel tovar",
      "pitcher": "clayton kershaw",
      "result": "In play, out(s)",
      "pitch": "4-Seam Fastball"
    },
    "50": {
      "player": "tyler freeman",
      "pitcher": "clayton kershaw",
      "result": "In play, out(s)",
      "pitch": "Slider"
    },
    "49": {
      "player": "michael conforto",
      "pitcher": "nick anderson",
      "result": "In play, out(s)",
      "pitch": "4-Seam Fastball"
    },
    "48": {
      "player": "will smith",
      "pitcher": "nick anderson",
      "result": "Called Strike",
      "pitch": "Curveball"
    },
    "47": {
      "player": "freddie freeman",
      "pitcher": "nick anderson",
      "result": "In play, out(s)",
      "pitch": "4-Seam Fastball"
    },
    "46": {
      "player": "ryan ritter",
      "pitcher": "clayton kershaw",
      "result": "In play, out(s)",
      "pitch": "Slider"
    },
    "45": {
      "player": "orlando arcia",
      "pitcher": "clayton kershaw",
      "result": "In play, out(s)",
      "pitch": "4-Seam Fastball"
    },
    "44": {
      "player": "kyle farmer",
      "pitcher": "clayton kershaw",
      "result": "Swinging Strike",
      "pitch": "Slider"
    },
    "43": {
      "player": "mookie betts",
      "pitcher": "nick anderson",
      "result": "In play, out(s)",
      "pitch": "Curveball"
    },
    "42": {
      "player": "miguel rojas",
      "pitcher": "nick anderson",
      "result": "Swinging Strike",
      "pitch": "4-Seam Fastball"
    },
    "41": {
      "player": "alex call",
      "pitcher": "nick anderson",
      "result": "Ball",
      "pitch": "4-Seam Fastball"
    },
    "40": {
      "player": "andy pages",
      "pitcher": "nick anderson",
      "result": "In play, run(s)",
      "pitch": "4-Seam Fastball"
    },
    "39": {
      "player": "braxton fulford",
      "pitcher": "clayton kershaw",
      "result": "In play, out(s)",
      "pitch": "Splitter"
    },
    "38": {
      "player": "brenton doyle",
      "pitcher": "clayton kershaw",
      "result": "In play, run(s)",
      "pitch": "Curveball"
    },
    "37": {
      "player": "jordan beck",
      "pitcher": "clayton kershaw",
      "result": "In play, no out",
      "pitch": "4-Seam Fastball"
    },
    "36": {
      "player": "hunter goodman",
      "pitcher": "clayton kershaw",
      "result": "In play, no out",
      "pitch": "Slider"
    },
    "35": {
      "player": "ezequiel tovar",
      "pitcher": "clayton kershaw",
      "result": "Swinging Strike",
      "pitch": "Curveball"
    },
    "34": {
      "player": "dalton rushing",
      "pitcher": "nick anderson",
      "result": "In play, out(s)",
      "pitch": "Changeup"
    },
    "33": {
      "player": "alex freeland",
      "pitcher": "chase dollander",
      "result": "In play, run(s)",
      "pitch": "4-Seam Fastball"
    },
    "32": {
      "player": "michael conforto",
      "pitcher": "chase dollander",
      "result": "In play, run(s)",
      "pitch": "Sinker"
    },
    "31": {
      "player": "will smith",
      "pitcher": "chase dollander",
      "result": "In play, out(s)",
      "pitch": "Sinker"
    },
    "30": {
      "player": "freddie freeman",
      "pitcher": "chase dollander",
      "result": "In play, no out",
      "pitch": "4-Seam Fastball"
    },
    "29": {
      "player": "mookie betts",
      "pitcher": "chase dollander",
      "result": "In play, no out",
      "pitch": "4-Seam Fastball"
    },
    "28": {
      "player": "tyler freeman",
      "pitcher": "clayton kershaw",
      "result": "In play, out(s)",
      "pitch": "4-Seam Fastball"
    },
    "27": {
      "player": "ryan ritter",
      "pitcher": "clayton kershaw",
      "result": "Swinging Strike",
      "pitch": "Slider"
    },
    "26": {
      "player": "orlando arcia",
      "pitcher": "clayton kershaw",
      "result": "In play, out(s)",
      "pitch": "Slider"
    },
    "25": {
      "player": "miguel rojas",
      "pitcher": "chase dollander",
      "result": "In play, out(s)",
      "pitch": "Sinker"
    },
    "24": {
      "player": "alex call",
      "pitcher": "chase dollander",
      "result": "In play, run(s)",
      "pitch": "Curveball"
    },
    "23": {
      "player": "andy pages",
      "pitcher": "chase dollander",
      "result": "Called Strike",
      "pitch": "4-Seam Fastball"
    },
    "22": {
      "player": "dalton rushing",
      "pitcher": "chase dollander",
      "result": "Swinging Strike",
      "pitch": "Changeup"
    },
    "21": {
      "player": "alex freeland",
      "pitcher": "chase dollander",
      "result": "In play, no out",
      "pitch": "Sinker"
    },
    "20": {
      "player": "kyle farmer",
      "pitcher": "clayton kershaw",
      "result": "In play, out(s)",
      "pitch": "4-Seam Fastball"
    },
    "19": {
      "player": "braxton fulford",
      "pitcher": "clayton kershaw",
      "result": "In play, no out",
      "pitch": "Slider"
    },
    "18": {
      "player": "brenton doyle",
      "pitcher": "clayton kershaw",
      "result": "In play, out(s)",
      "pitch": "Slider"
    },
    "17": {
      "player": "michael conforto",
      "pitcher": "chase dollander",
      "result": "Swinging Strike",
      "pitch": "Curveball"
    },
    "16": {
      "player": "will smith",
      "pitcher": "chase dollander",
      "result": "Hit By Pitch",
      "pitch": "Sinker"
    },
    "15": {
      "player": "freddie freeman",
      "pitcher": "chase dollander",
      "result": "Swinging Strike",
      "pitch": "Sinker"
    },
    "14": {
      "player": "mookie betts",
      "pitcher": "chase dollander",
      "result": "In play, no out",
      "pitch": "Cutter"
    },
    "13": {
      "player": "miguel rojas",
      "pitcher": "chase dollander",
      "result": "In play, run(s)",
      "pitch": "4-Seam Fastball"
    },
    "12": {
      "player": "alex call",
      "pitcher": "chase dollander",
      "result": "Ball",
      "pitch": "4-Seam Fastball"
    },
    "11": {
      "player": "andy pages",
      "pitcher": "chase dollander",
      "result": "In play, no out",
      "pitch": "Sinker"
    },
    "10": {
      "player": "dalton rushing",
      "pitcher": "chase dollander",
      "result": "In play, out(s)",
      "pitch": "Sinker"
    },
    "9": {
      "player": "jordan beck",
      "pitcher": "clayton kershaw",
      "result": "In play, out(s)",
      "pitch": "Slider"
    },
    "8": {
      "player": "hunter goodman",
      "pitcher": "clayton kershaw",
      "result": "In play, run(s)",
      "pitch": "Slider"
    },
    "7": {
      "player": "ezequiel tovar",
      "pitcher": "clayton kershaw",
      "result": "In play, out(s)",
      "pitch": "Slider"
    },
    "6": {
      "player": "tyler freeman",
      "pitcher": "clayton kershaw",
      "result": "In play, no out",
      "pitch": "Curveball"
    },
    "5": {
      "player": "alex freeland",
      "pitcher": "chase dollander",
      "result": "In play, out(s)",
      "pitch": "4-Seam Fastball"
    },
    "4": {
      "player": "michael conforto",
      "pitcher": "chase dollander",
      "result": "In play, out(s)",
      "pitch": "Sinker"
    },
    "3": {
      "player": "will smith",
      "pitcher": "chase dollander",
      "result": "Called Strike",
      "pitch": "4-Seam Fastball"
    },
    "2": {
      "player": "freddie freeman",
      "pitcher": "chase dollander",
      "result": "In play, run(s)",
      "pitch": "4-Seam Fastball"
    },
    "1": {
      "player": "mookie betts",
      "pitcher": "chase dollander",
      "result": "Ball",
      "pitch": "4-Seam Fastball"
    }
  },
  "nym @ wsh": {
    "61": {
      "player": "andres chaparro",
      "pitcher": "brooks raley",
      "result": "Swinging Strike",
      "pitch": "Changeup"
    },
    "60": {
      "player": "paul dejong",
      "pitcher": "brooks raley",
      "result": "In play, out(s)",
      "pitch": "Cutter"
    },
    "59": {
      "player": "cj abrams",
      "pitcher": "brooks raley",
      "result": "Called Strike",
      "pitch": "Sweeper"
    },
    "58": {
      "player": "starling marte",
      "pitcher": "pj poulin",
      "result": "In play, out(s)",
      "pitch": "4-Seam Fastball"
    },
    "57": {
      "player": "juan soto",
      "pitcher": "pj poulin",
      "result": "Swinging Strike",
      "pitch": "4-Seam Fastball"
    },
    "56": {
      "player": "francisco lindor",
      "pitcher": "pj poulin",
      "result": "In play, out(s)",
      "pitch": "4-Seam Fastball"
    },
    "55": {
      "player": "james wood",
      "pitcher": "brooks raley",
      "result": "Swinging Strike",
      "pitch": "Sweeper"
    },
    "54": {
      "player": "jacob young",
      "pitcher": "tyler rogers",
      "result": "In play, run(s)",
      "pitch": "Sinker"
    },
    "53": {
      "player": "brady house",
      "pitcher": "tyler rogers",
      "result": "Called Strike",
      "pitch": "Slider"
    },
    "52": {
      "player": "daylen lile",
      "pitcher": "tyler rogers",
      "result": "In play, no out",
      "pitch": "Sinker"
    },
    "51": {
      "player": "dylan crews",
      "pitcher": "tyler rogers",
      "result": "Swinging Strike",
      "pitch": "Slider"
    },
    "50": {
      "player": "hayden senger",
      "pitcher": "clayton beeter",
      "result": "In play, out(s)",
      "pitch": "4-Seam Fastball"
    },
    "49": {
      "player": "cedric mullins",
      "pitcher": "clayton beeter",
      "result": "In play, out(s)",
      "pitch": "4-Seam Fastball"
    },
    "48": {
      "player": "tyrone taylor",
      "pitcher": "clayton beeter",
      "result": "In play, out(s)",
      "pitch": "Slider"
    },
    "47": {
      "player": "riley adams",
      "pitcher": "tyler rogers",
      "result": "In play, run(s)",
      "pitch": "Sinker"
    },
    "46": {
      "player": "andres chaparro",
      "pitcher": "sean manaea",
      "result": "Ball",
      "pitch": "4-Seam Fastball"
    },
    "45": {
      "player": "paul dejong",
      "pitcher": "sean manaea",
      "result": "In play, run(s)",
      "pitch": "Sweeper"
    },
    "44": {
      "player": "cj abrams",
      "pitcher": "sean manaea",
      "result": "Hit By Pitch",
      "pitch": "4-Seam Fastball"
    },
    "43": {
      "player": "james wood",
      "pitcher": "sean manaea",
      "result": "In play, out(s)",
      "pitch": "Sweeper"
    },
    "42": {
      "player": "jacob young",
      "pitcher": "sean manaea",
      "result": "In play, no out",
      "pitch": "4-Seam Fastball"
    },
    "41": {
      "player": "brady house",
      "pitcher": "sean manaea",
      "result": "In play, no out",
      "pitch": "Changeup"
    },
    "40": {
      "player": "brett baty",
      "pitcher": "jackson rutledge",
      "result": "Swinging Strike",
      "pitch": "Slider"
    },
    "39": {
      "player": "mark vientos",
      "pitcher": "jackson rutledge",
      "result": "In play, out(s)",
      "pitch": "Sinker"
    },
    "38": {
      "player": "pete alonso",
      "pitcher": "mackenzie gore",
      "result": "Ball",
      "pitch": "Curveball"
    },
    "37": {
      "player": "starling marte",
      "pitcher": "mackenzie gore",
      "result": "Ball",
      "pitch": "4-Seam Fastball"
    },
    "36": {
      "player": "juan soto",
      "pitcher": "mackenzie gore",
      "result": "In play, out(s)",
      "pitch": "Curveball"
    },
    "35": {
      "player": "daylen lile",
      "pitcher": "sean manaea",
      "result": "In play, out(s)",
      "pitch": "4-Seam Fastball"
    },
    "34": {
      "player": "dylan crews",
      "pitcher": "sean manaea",
      "result": "In play, run(s)",
      "pitch": "4-Seam Fastball"
    },
    "33": {
      "player": "riley adams",
      "pitcher": "sean manaea",
      "result": "Hit By Pitch",
      "pitch": "Sweeper"
    },
    "32": {
      "player": "andres chaparro",
      "pitcher": "sean manaea",
      "result": "In play, no out",
      "pitch": "4-Seam Fastball"
    },
    "31": {
      "player": "paul dejong",
      "pitcher": "sean manaea",
      "result": "In play, out(s)",
      "pitch": "Sweeper"
    },
    "30": {
      "player": "cj abrams",
      "pitcher": "sean manaea",
      "result": "Swinging Strike",
      "pitch": "Sweeper"
    },
    "29": {
      "player": "francisco lindor",
      "pitcher": "mackenzie gore",
      "result": "In play, out(s)",
      "pitch": "4-Seam Fastball"
    },
    "28": {
      "player": "hayden senger",
      "pitcher": "mackenzie gore",
      "result": "In play, run(s)",
      "pitch": "4-Seam Fastball"
    },
    "27": {
      "player": "cedric mullins",
      "pitcher": "mackenzie gore",
      "result": "In play, no out",
      "pitch": "Slider"
    },
    "26": {
      "player": "tyrone taylor",
      "pitcher": "mackenzie gore",
      "result": "Ball",
      "pitch": "4-Seam Fastball"
    },
    "25": {
      "player": "brett baty",
      "pitcher": "mackenzie gore",
      "result": "In play, no out",
      "pitch": "4-Seam Fastball"
    },
    "24": {
      "player": "mark vientos",
      "pitcher": "mackenzie gore",
      "result": "In play, out(s)",
      "pitch": "Changeup"
    },
    "23": {
      "player": "james wood",
      "pitcher": "sean manaea",
      "result": "Swinging Strike",
      "pitch": "4-Seam Fastball"
    },
    "22": {
      "player": "jacob young",
      "pitcher": "sean manaea",
      "result": "Swinging Strike",
      "pitch": "4-Seam Fastball"
    },
    "21": {
      "player": "brady house",
      "pitcher": "sean manaea",
      "result": "In play, no out",
      "pitch": "4-Seam Fastball"
    },
    "20": {
      "player": "daylen lile",
      "pitcher": "sean manaea",
      "result": "In play, out(s)",
      "pitch": "4-Seam Fastball"
    },
    "19": {
      "player": "pete alonso",
      "pitcher": "mackenzie gore",
      "result": "In play, out(s)",
      "pitch": "Curveball"
    },
    "18": {
      "player": "starling marte",
      "pitcher": "mackenzie gore",
      "result": "In play, run(s)",
      "pitch": "Curveball"
    },
    "17": {
      "player": "juan soto",
      "pitcher": "mackenzie gore",
      "result": "In play, out(s)",
      "pitch": "Cutter"
    },
    "16": {
      "player": "francisco lindor",
      "pitcher": "mackenzie gore",
      "result": "In play, no out",
      "pitch": "Curveball"
    },
    "15": {
      "player": "dylan crews",
      "pitcher": "sean manaea",
      "result": "Called Strike",
      "pitch": "4-Seam Fastball"
    },
    "14": {
      "player": "riley adams",
      "pitcher": "sean manaea",
      "result": "Foul Tip",
      "pitch": "4-Seam Fastball"
    },
    "13": {
      "player": "andres chaparro",
      "pitcher": "sean manaea",
      "result": "Swinging Strike",
      "pitch": "Sweeper"
    },
    "12": {
      "player": "hayden senger",
      "pitcher": "mackenzie gore",
      "result": "Swinging Strike",
      "pitch": "Curveball"
    },
    "11": {
      "player": "cedric mullins",
      "pitcher": "mackenzie gore",
      "result": "Ball In Dirt",
      "pitch": "Curveball"
    },
    "10": {
      "player": "tyrone taylor",
      "pitcher": "mackenzie gore",
      "result": "In play, out(s)",
      "pitch": "Curveball"
    },
    "9": {
      "player": "brett baty",
      "pitcher": "mackenzie gore",
      "result": "Swinging Strike",
      "pitch": "Slider"
    },
    "8": {
      "player": "mark vientos",
      "pitcher": "mackenzie gore",
      "result": "In play, no out",
      "pitch": "Cutter"
    },
    "7": {
      "player": "paul dejong",
      "pitcher": "sean manaea",
      "result": "Called Strike",
      "pitch": "Sweeper"
    },
    "6": {
      "player": "cj abrams",
      "pitcher": "sean manaea",
      "result": "In play, out(s)",
      "pitch": "4-Seam Fastball"
    },
    "5": {
      "player": "james wood",
      "pitcher": "sean manaea",
      "result": "Called Strike",
      "pitch": "Sweeper"
    },
    "4": {
      "player": "pete alonso",
      "pitcher": "mackenzie gore",
      "result": "Called Strike",
      "pitch": "Curveball"
    },
    "3": {
      "player": "starling marte",
      "pitcher": "mackenzie gore",
      "result": "Swinging Strike",
      "pitch": "Curveball"
    },
    "2": {
      "player": "juan soto",
      "pitcher": "mackenzie gore",
      "result": "Foul Tip",
      "pitch": "Curveball"
    },
    "1": {
      "player": "francisco lindor",
      "pitcher": "mackenzie gore",
      "result": "In play, run(s)",
      "pitch": "4-Seam Fastball"
    }
  },
  "sf @ sd": {
    "54": {
      "player": "luis arraez",
      "pitcher": "joel peguero",
      "result": "In play, no out",
      "pitch": "Slider"
    },
    "53": {
      "player": "fernando tatis",
      "pitcher": "joel peguero",
      "result": "In play, out(s)",
      "pitch": "Sinker"
    },
    "52": {
      "player": "freddy fermin",
      "pitcher": "joel peguero",
      "result": "In play, out(s)",
      "pitch": "Slider"
    },
    "51": {
      "player": "christian koss",
      "pitcher": "jeremiah estrada",
      "result": "In play, out(s)",
      "pitch": "Splitter"
    },
    "50": {
      "player": "casey schmitt",
      "pitcher": "jeremiah estrada",
      "result": "Ball",
      "pitch": "Slider"
    },
    "49": {
      "player": "dominic smith",
      "pitcher": "jeremiah estrada",
      "result": "In play, out(s)",
      "pitch": "4-Seam Fastball"
    },
    "48": {
      "player": "willy adames",
      "pitcher": "dylan cease",
      "result": "In play, run(s)",
      "pitch": "4-Seam Fastball"
    },
    "47": {
      "player": "rafael devers",
      "pitcher": "dylan cease",
      "result": "In play, run(s)",
      "pitch": "4-Seam Fastball"
    },
    "46": {
      "player": "jake cronenworth",
      "pitcher": "matt gage",
      "result": "Swinging Strike",
      "pitch": "Slider"
    },
    "45": {
      "player": "ramon laureano",
      "pitcher": "matt gage",
      "result": "In play, run(s)",
      "pitch": "4-Seam Fastball"
    },
    "44": {
      "player": "gavin sheets",
      "pitcher": "matt gage",
      "result": "In play, out(s)",
      "pitch": "4-Seam Fastball"
    },
    "43": {
      "player": "xander bogaerts",
      "pitcher": "matt gage",
      "result": "In play, run(s)",
      "pitch": "Changeup"
    },
    "42": {
      "player": "ryan ohearn",
      "pitcher": "matt gage",
      "result": "Hit By Pitch",
      "pitch": "Sinker"
    },
    "41": {
      "player": "manny machado",
      "pitcher": "justin verlander",
      "result": "In play, run(s)",
      "pitch": "4-Seam Fastball"
    },
    "40": {
      "player": "luis arraez",
      "pitcher": "justin verlander",
      "result": "In play, out(s)",
      "pitch": "4-Seam Fastball"
    },
    "39": {
      "player": "fernando tatis",
      "pitcher": "justin verlander",
      "result": "In play, no out",
      "pitch": "4-Seam Fastball"
    },
    "38": {
      "player": "freddy fermin",
      "pitcher": "justin verlander",
      "result": "In play, run(s)",
      "pitch": "4-Seam Fastball"
    },
    "37": {
      "player": "jake cronenworth",
      "pitcher": "justin verlander",
      "result": "Ball",
      "pitch": "Slider"
    },
    "36": {
      "player": "ramon laureano",
      "pitcher": "justin verlander",
      "result": "In play, no out",
      "pitch": "Curveball"
    },
    "35": {
      "player": "heliot ramos",
      "pitcher": "dylan cease",
      "result": "Swinging Strike",
      "pitch": "4-Seam Fastball"
    },
    "34": {
      "player": "jung hoo lee",
      "pitcher": "dylan cease",
      "result": "Ball",
      "pitch": "4-Seam Fastball"
    },
    "33": {
      "player": "andrew knizner",
      "pitcher": "dylan cease",
      "result": "In play, out(s)",
      "pitch": "Sinker"
    },
    "32": {
      "player": "luis matos",
      "pitcher": "dylan cease",
      "result": "Swinging Strike",
      "pitch": "Slider"
    },
    "31": {
      "player": "gavin sheets",
      "pitcher": "justin verlander",
      "result": "In play, out(s)",
      "pitch": "Curveball"
    },
    "30": {
      "player": "xander bogaerts",
      "pitcher": "justin verlander",
      "result": "In play, run(s)",
      "pitch": "Sweeper"
    },
    "29": {
      "player": "ryan ohearn",
      "pitcher": "justin verlander",
      "result": "Swinging Strike",
      "pitch": "Slider"
    },
    "28": {
      "player": "manny machado",
      "pitcher": "justin verlander",
      "result": "In play, run(s)",
      "pitch": "Slider"
    },
    "27": {
      "player": "luis arraez",
      "pitcher": "justin verlander",
      "result": "In play, no out",
      "pitch": "4-Seam Fastball"
    },
    "26": {
      "player": "fernando tatis",
      "pitcher": "justin verlander",
      "result": "In play, no out",
      "pitch": "4-Seam Fastball"
    },
    "25": {
      "player": "christian koss",
      "pitcher": "dylan cease",
      "result": "Swinging Strike",
      "pitch": "4-Seam Fastball"
    },
    "24": {
      "player": "casey schmitt",
      "pitcher": "dylan cease",
      "result": "In play, no out",
      "pitch": "Slider"
    },
    "23": {
      "player": "dominic smith",
      "pitcher": "dylan cease",
      "result": "Called Strike",
      "pitch": "4-Seam Fastball"
    },
    "22": {
      "player": "willy adames",
      "pitcher": "dylan cease",
      "result": "Swinging Strike",
      "pitch": "Slider"
    },
    "21": {
      "player": "freddy fermin",
      "pitcher": "justin verlander",
      "result": "In play, out(s)",
      "pitch": "4-Seam Fastball"
    },
    "20": {
      "player": "jake cronenworth",
      "pitcher": "justin verlander",
      "result": "Swinging Strike",
      "pitch": "Curveball"
    },
    "19": {
      "player": "ramon laureano",
      "pitcher": "justin verlander",
      "result": "In play, out(s)",
      "pitch": "Changeup"
    },
    "18": {
      "player": "rafael devers",
      "pitcher": "dylan cease",
      "result": "In play, out(s)",
      "pitch": "4-Seam Fastball"
    },
    "17": {
      "player": "heliot ramos",
      "pitcher": "dylan cease",
      "result": "In play, run(s)",
      "pitch": "Slider"
    },
    "16": {
      "player": "jung hoo lee",
      "pitcher": "dylan cease",
      "result": "In play, no out",
      "pitch": "Knuckle Curve"
    },
    "15": {
      "player": "andrew knizner",
      "pitcher": "dylan cease",
      "result": "In play, run(s)",
      "pitch": "Slider"
    },
    "14": {
      "player": "luis matos",
      "pitcher": "dylan cease",
      "result": "In play, no out",
      "pitch": "4-Seam Fastball"
    },
    "13": {
      "player": "gavin sheets",
      "pitcher": "justin verlander",
      "result": "Swinging Strike",
      "pitch": "Slider"
    },
    "12": {
      "player": "xander bogaerts",
      "pitcher": "justin verlander",
      "result": "In play, out(s)",
      "pitch": "Sweeper"
    },
    "11": {
      "player": "ryan ohearn",
      "pitcher": "justin verlander",
      "result": "Swinging Strike",
      "pitch": "Slider"
    },
    "10": {
      "player": "christian koss",
      "pitcher": "dylan cease",
      "result": "Swinging Strike",
      "pitch": "Slider"
    },
    "9": {
      "player": "casey schmitt",
      "pitcher": "dylan cease",
      "result": "In play, out(s)",
      "pitch": "4-Seam Fastball"
    },
    "8": {
      "player": "dominic smith",
      "pitcher": "dylan cease",
      "result": "Swinging Strike",
      "pitch": "4-Seam Fastball"
    },
    "7": {
      "player": "willy adames",
      "pitcher": "dylan cease",
      "result": "Ball",
      "pitch": "Slider"
    },
    "6": {
      "player": "manny machado",
      "pitcher": "justin verlander",
      "result": "In play, out(s)",
      "pitch": "Sweeper"
    },
    "5": {
      "player": "luis arraez",
      "pitcher": "justin verlander",
      "result": "In play, out(s)",
      "pitch": "Changeup"
    },
    "4": {
      "player": "fernando tatis",
      "pitcher": "justin verlander",
      "result": "In play, out(s)",
      "pitch": "4-Seam Fastball"
    },
    "3": {
      "player": "rafael devers",
      "pitcher": "dylan cease",
      "result": "In play, out(s)",
      "pitch": "4-Seam Fastball"
    },
    "2": {
      "player": "heliot ramos",
      "pitcher": "dylan cease",
      "result": "In play, out(s)",
      "pitch": "Sinker"
    },
    "1": {
      "player": "jung hoo lee",
      "pitcher": "dylan cease",
      "result": "In play, no out",
      "pitch": "4-Seam Fastball"
    }
  },
  "hou @ bal": {},
  "bos @ nyy": {},
  "stl @ tb": {}
}