{
  "chc @ pit": {
    "87": {
      "player": "oneil cruz",
      "pitcher": "taylor rogers",
      "result": "In play, out(s)",
      "pitch": "Sweeper"
    },
    "86": {
      "player": "joey bart",
      "pitcher": "taylor rogers",
      "result": "In play, out(s)",
      "pitch": "Sinker"
    },
    "85": {
      "player": "andrew mccutchen",
      "pitcher": "taylor rogers",
      "result": "In play, out(s)",
      "pitch": "Sinker"
    },
    "84": {
      "player": "matt shaw",
      "pitcher": "dennis santana",
      "result": "In play, out(s)",
      "pitch": "Slider"
    },
    "83": {
      "player": "reese mcguire",
      "pitcher": "dennis santana",
      "result": "In play, out(s)",
      "pitch": "4-Seam Fastball"
    },
    "82": {
      "player": "dansby swanson",
      "pitcher": "dennis santana",
      "result": "Swinging Strike",
      "pitch": "4-Seam Fastball"
    },
    "81": {
      "player": "tommy pham",
      "pitcher": "drew pomeranz",
      "result": "In play, out(s)",
      "pitch": "4-Seam Fastball"
    },
    "80": {
      "player": "nick gonzales",
      "pitcher": "drew pomeranz",
      "result": "In play, out(s)",
      "pitch": "4-Seam Fastball"
    },
    "79": {
      "player": "jared triolo",
      "pitcher": "drew pomeranz",
      "result": "In play, no out",
      "pitch": "4-Seam Fastball"
    },
    "78": {
      "player": "jack suwinski",
      "pitcher": "drew pomeranz",
      "result": "Swinging Strike",
      "pitch": "4-Seam Fastball"
    },
    "77": {
      "player": "rafael flores",
      "pitcher": "drew pomeranz",
      "result": "Ball",
      "pitch": "Knuckle Curve"
    },
    "76": {
      "player": "pete crow armstrong",
      "pitcher": "kyle nicolas",
      "result": "In play, out(s)",
      "pitch": "Slider"
    },
    "75": {
      "player": "kevin alcantara",
      "pitcher": "kyle nicolas",
      "result": "Called Strike",
      "pitch": "Curveball"
    },
    "74": {
      "player": "justin turner",
      "pitcher": "kyle nicolas",
      "result": "In play, run(s)",
      "pitch": "4-Seam Fastball"
    },
    "73": {
      "player": "ian happ",
      "pitcher": "dauri moreta",
      "result": "Ball In Dirt",
      "pitch": "Slider"
    },
    "72": {
      "player": "nico hoerner",
      "pitcher": "dauri moreta",
      "result": "Ball",
      "pitch": "4-Seam Fastball"
    },
    "71": {
      "player": "michael busch",
      "pitcher": "dauri moreta",
      "result": "In play, out(s)",
      "pitch": "4-Seam Fastball"
    },
    "70": {
      "player": "nick yorke",
      "pitcher": "aaron civale",
      "result": "In play, out(s)",
      "pitch": "Cutter"
    },
    "69": {
      "player": "oneil cruz",
      "pitcher": "aaron civale",
      "result": "In play, out(s)",
      "pitch": "Curveball"
    },
    "68": {
      "player": "joey bart",
      "pitcher": "aaron civale",
      "result": "Hit By Pitch",
      "pitch": "Curveball"
    },
    "67": {
      "player": "andrew mccutchen",
      "pitcher": "aaron civale",
      "result": "Called Strike",
      "pitch": "Curveball"
    },
    "66": {
      "player": "matt shaw",
      "pitcher": "dauri moreta",
      "result": "In play, out(s)",
      "pitch": "Slider"
    },
    "65": {
      "player": "reese mcguire",
      "pitcher": "dauri moreta",
      "result": "In play, no out",
      "pitch": "4-Seam Fastball"
    },
    "64": {
      "player": "dansby swanson",
      "pitcher": "dauri moreta",
      "result": "Ball",
      "pitch": "Slider"
    },
    "63": {
      "player": "pete crow armstrong",
      "pitcher": "dauri moreta",
      "result": "Foul Tip",
      "pitch": "Slider"
    },
    "62": {
      "player": "tommy pham",
      "pitcher": "aaron civale",
      "result": "In play, out(s)",
      "pitch": "Curveball"
    },
    "61": {
      "player": "nick gonzales",
      "pitcher": "aaron civale",
      "result": "In play, no out",
      "pitch": "Curveball"
    },
    "60": {
      "player": "jared triolo",
      "pitcher": "aaron civale",
      "result": "In play, out(s)",
      "pitch": "Cutter"
    },
    "59": {
      "player": "jack suwinski",
      "pitcher": "aaron civale",
      "result": "Swinging Strike",
      "pitch": "Cutter"
    },
    "58": {
      "player": "seiya suzuki",
      "pitcher": "evan sisk",
      "result": "In play, out(s)",
      "pitch": "Curveball"
    },
    "57": {
      "player": "justin turner",
      "pitcher": "evan sisk",
      "result": "In play, run(s)",
      "pitch": "4-Seam Fastball"
    },
    "56": {
      "player": "ian happ",
      "pitcher": "evan sisk",
      "result": "In play, run(s)",
      "pitch": "4-Seam Fastball"
    },
    "55": {
      "player": "nico hoerner",
      "pitcher": "yohan ramirez",
      "result": "In play, no out",
      "pitch": "4-Seam Fastball"
    },
    "54": {
      "player": "michael busch",
      "pitcher": "yohan ramirez",
      "result": "In play, out(s)",
      "pitch": "Curveball"
    },
    "53": {
      "player": "matt shaw",
      "pitcher": "yohan ramirez",
      "result": "Ball",
      "pitch": "Sinker"
    },
    "52": {
      "player": "reese mcguire",
      "pitcher": "yohan ramirez",
      "result": "In play, out(s)",
      "pitch": "4-Seam Fastball"
    },
    "51": {
      "player": "dansby swanson",
      "pitcher": "yohan ramirez",
      "result": "In play, no out",
      "pitch": "Curveball"
    },
    "50": {
      "player": "rafael flores",
      "pitcher": "aaron civale",
      "result": "In play, out(s)",
      "pitch": "Cutter"
    },
    "49": {
      "player": "nick yorke",
      "pitcher": "aaron civale",
      "result": "Swinging Strike",
      "pitch": "4-Seam Fastball"
    },
    "48": {
      "player": "alexander canario",
      "pitcher": "aaron civale",
      "result": "In play, out(s)",
      "pitch": "Sinker"
    },
    "47": {
      "player": "pete crow armstrong",
      "pitcher": "johan oviedo",
      "result": "In play, out(s)",
      "pitch": "4-Seam Fastball"
    },
    "46": {
      "player": "seiya suzuki",
      "pitcher": "johan oviedo",
      "result": "In play, out(s)",
      "pitch": "Slider"
    },
    "45": {
      "player": "moises ballesteros",
      "pitcher": "johan oviedo",
      "result": "In play, out(s)",
      "pitch": "Slider"
    },
    "44": {
      "player": "joey bart",
      "pitcher": "porter hodge",
      "result": "Swinging Strike",
      "pitch": "Slider"
    },
    "43": {
      "player": "andrew mccutchen",
      "pitcher": "porter hodge",
      "result": "Swinging Strike",
      "pitch": "Slider"
    },
    "42": {
      "player": "tommy pham",
      "pitcher": "porter hodge",
      "result": "In play, out(s)",
      "pitch": "4-Seam Fastball"
    },
    "41": {
      "player": "nick gonzales",
      "pitcher": "porter hodge",
      "result": "In play, no out",
      "pitch": "Slider"
    },
    "40": {
      "player": "ian happ",
      "pitcher": "johan oviedo",
      "result": "In play, out(s)",
      "pitch": "Curveball"
    },
    "39": {
      "player": "nico hoerner",
      "pitcher": "johan oviedo",
      "result": "In play, no out",
      "pitch": "Slider"
    },
    "38": {
      "player": "michael busch",
      "pitcher": "johan oviedo",
      "result": "Swinging Strike",
      "pitch": "Curveball"
    },
    "37": {
      "player": "matt shaw",
      "pitcher": "johan oviedo",
      "result": "In play, out(s)",
      "pitch": "Sinker"
    },
    "36": {
      "player": "jared triolo",
      "pitcher": "matthew boyd",
      "result": "Called Strike",
      "pitch": "4-Seam Fastball"
    },
    "35": {
      "player": "cam devanney",
      "pitcher": "matthew boyd",
      "result": "Swinging Strike",
      "pitch": "Changeup"
    },
    "34": {
      "player": "rafael flores",
      "pitcher": "matthew boyd",
      "result": "In play, no out",
      "pitch": "Changeup"
    },
    "33": {
      "player": "nick yorke",
      "pitcher": "matthew boyd",
      "result": "In play, out(s)",
      "pitch": "Changeup"
    },
    "32": {
      "player": "reese mcguire",
      "pitcher": "johan oviedo",
      "result": "In play, out(s)",
      "pitch": "4-Seam Fastball"
    },
    "31": {
      "player": "dansby swanson",
      "pitcher": "johan oviedo",
      "result": "Swinging Strike",
      "pitch": "4-Seam Fastball"
    },
    "30": {
      "player": "pete crow armstrong",
      "pitcher": "johan oviedo",
      "result": "In play, no out",
      "pitch": "4-Seam Fastball"
    },
    "29": {
      "player": "seiya suzuki",
      "pitcher": "johan oviedo",
      "result": "In play, out(s)",
      "pitch": "Sinker"
    },
    "28": {
      "player": "alexander canario",
      "pitcher": "matthew boyd",
      "result": "Swinging Strike",
      "pitch": "Changeup"
    },
    "27": {
      "player": "joey bart",
      "pitcher": "matthew boyd",
      "result": "Swinging Strike",
      "pitch": "Curveball"
    },
    "26": {
      "player": "andrew mccutchen",
      "pitcher": "matthew boyd",
      "result": "Ball",
      "pitch": "4-Seam Fastball"
    },
    "25": {
      "player": "tommy pham",
      "pitcher": "matthew boyd",
      "result": "In play, out(s)",
      "pitch": "Curveball"
    },
    "24": {
      "player": "nick gonzales",
      "pitcher": "matthew boyd",
      "result": "Hit By Pitch",
      "pitch": "Slider"
    },
    "23": {
      "player": "jared triolo",
      "pitcher": "matthew boyd",
      "result": "In play, no out",
      "pitch": "Sinker"
    },
    "22": {
      "player": "cam devanney",
      "pitcher": "matthew boyd",
      "result": "In play, no out",
      "pitch": "4-Seam Fastball"
    },
    "21": {
      "player": "moises ballesteros",
      "pitcher": "johan oviedo",
      "result": "Swinging Strike",
      "pitch": "4-Seam Fastball"
    },
    "20": {
      "player": "ian happ",
      "pitcher": "johan oviedo",
      "result": "In play, out(s)",
      "pitch": "Slider"
    },
    "19": {
      "player": "nico hoerner",
      "pitcher": "johan oviedo",
      "result": "In play, out(s)",
      "pitch": "Slider"
    },
    "18": {
      "player": "michael busch",
      "pitcher": "johan oviedo",
      "result": "Ball",
      "pitch": "Slider"
    },
    "17": {
      "player": "matt shaw",
      "pitcher": "johan oviedo",
      "result": "Ball",
      "pitch": "4-Seam Fastball"
    },
    "16": {
      "player": "rafael flores",
      "pitcher": "matthew boyd",
      "result": "Swinging Strike",
      "pitch": "Changeup"
    },
    "15": {
      "player": "nick yorke",
      "pitcher": "matthew boyd",
      "result": "In play, no out",
      "pitch": "Changeup"
    },
    "14": {
      "player": "alexander canario",
      "pitcher": "matthew boyd",
      "result": "In play, no out",
      "pitch": "4-Seam Fastball"
    },
    "13": {
      "player": "joey bart",
      "pitcher": "matthew boyd",
      "result": "In play, run(s)",
      "pitch": "4-Seam Fastball"
    },
    "12": {
      "player": "andrew mccutchen",
      "pitcher": "matthew boyd",
      "result": "In play, no out",
      "pitch": "4-Seam Fastball"
    },
    "11": {
      "player": "tommy pham",
      "pitcher": "matthew boyd",
      "result": "Ball",
      "pitch": "Changeup"
    },
    "10": {
      "player": "nick gonzales",
      "pitcher": "matthew boyd",
      "result": "In play, out(s)",
      "pitch": "4-Seam Fastball"
    },
    "9": {
      "player": "jared triolo",
      "pitcher": "matthew boyd",
      "result": "In play, out(s)",
      "pitch": "Changeup"
    },
    "8": {
      "player": "reese mcguire",
      "pitcher": "johan oviedo",
      "result": "In play, out(s)",
      "pitch": "4-Seam Fastball"
    },
    "7": {
      "player": "dansby swanson",
      "pitcher": "johan oviedo",
      "result": "In play, no out",
      "pitch": "Sinker"
    },
    "6": {
      "player": "pete crow armstrong",
      "pitcher": "johan oviedo",
      "result": "In play, out(s)",
      "pitch": "4-Seam Fastball"
    },
    "5": {
      "player": "seiya suzuki",
      "pitcher": "johan oviedo",
      "result": "Hit By Pitch",
      "pitch": "Sinker"
    },
    "4": {
      "player": "moises ballesteros",
      "pitcher": "johan oviedo",
      "result": "In play, run(s)",
      "pitch": "4-Seam Fastball"
    },
    "3": {
      "player": "ian happ",
      "pitcher": "johan oviedo",
      "result": "In play, run(s)",
      "pitch": "Curveball"
    },
    "2": {
      "player": "nico hoerner",
      "pitcher": "johan oviedo",
      "result": "In play, no out",
      "pitch": "Curveball"
    },
    "1": {
      "player": "michael busch",
      "pitcher": "johan oviedo",
      "result": "Ball",
      "pitch": "Slider"
    }
  },
  "cin @ stl": {
    "76": {
      "player": "jordan walker",
      "pitcher": "emilio pagan",
      "result": "Called Strike",
      "pitch": "4-Seam Fastball"
    },
    "75": {
      "player": "jimmy crooks",
      "pitcher": "emilio pagan",
      "result": "Swinging Strike",
      "pitch": "Splitter"
    },
    "74": {
      "player": "thomas saggese",
      "pitcher": "emilio pagan",
      "result": "Ball",
      "pitch": "4-Seam Fastball"
    },
    "73": {
      "player": "nolan gorman",
      "pitcher": "emilio pagan",
      "result": "Swinging Strike",
      "pitch": "4-Seam Fastball"
    },
    "72": {
      "player": "santiago espinal",
      "pitcher": "gordon graceffo",
      "result": "In play, out(s)",
      "pitch": "Curveball"
    },
    "71": {
      "player": "austin hays",
      "pitcher": "gordon graceffo",
      "result": "In play, out(s)",
      "pitch": "4-Seam Fastball"
    },
    "70": {
      "player": "will benson",
      "pitcher": "gordon graceffo",
      "result": "Swinging Strike",
      "pitch": "Curveball"
    },
    "69": {
      "player": "nolan arenado",
      "pitcher": "chase burns",
      "result": "In play, out(s)",
      "pitch": "4-Seam Fastball"
    },
    "68": {
      "player": "alec burleson",
      "pitcher": "chase burns",
      "result": "Ball",
      "pitch": "4-Seam Fastball"
    },
    "67": {
      "player": "ivan herrera",
      "pitcher": "chase burns",
      "result": "In play, out(s)",
      "pitch": "4-Seam Fastball"
    },
    "66": {
      "player": "lars nootbaar",
      "pitcher": "chase burns",
      "result": "In play, no out",
      "pitch": "4-Seam Fastball"
    },
    "65": {
      "player": "victor scott",
      "pitcher": "chase burns",
      "result": "In play, out(s)",
      "pitch": "4-Seam Fastball"
    },
    "64": {
      "player": "noelvi marte",
      "pitcher": "ryan fernandez",
      "result": "In play, out(s)",
      "pitch": "4-Seam Fastball"
    },
    "63": {
      "player": "gavin lux",
      "pitcher": "ryan fernandez",
      "result": "Called Strike",
      "pitch": "Slider"
    },
    "62": {
      "player": "matt mclain",
      "pitcher": "ryan fernandez",
      "result": "Swinging Strike",
      "pitch": "Slider"
    },
    "61": {
      "player": "jordan walker",
      "pitcher": "chase burns",
      "result": "Swinging Strike",
      "pitch": "4-Seam Fastball"
    },
    "60": {
      "player": "jimmy crooks",
      "pitcher": "chase burns",
      "result": "In play, out(s)",
      "pitch": "4-Seam Fastball"
    },
    "59": {
      "player": "thomas saggese",
      "pitcher": "chase burns",
      "result": "In play, no out",
      "pitch": "Slider"
    },
    "58": {
      "player": "jose trevino",
      "pitcher": "matt svanson",
      "result": "Called Strike",
      "pitch": "Sweeper"
    },
    "57": {
      "player": "spencer steer",
      "pitcher": "matt svanson",
      "result": "In play, run(s)",
      "pitch": "Sweeper"
    },
    "56": {
      "player": "elly de la cruz",
      "pitcher": "matt svanson",
      "result": "Called Strike",
      "pitch": "Sweeper"
    },
    "55": {
      "player": "sal stewart",
      "pitcher": "matt svanson",
      "result": "In play, no out",
      "pitch": "Sweeper"
    },
    "54": {
      "player": "austin hays",
      "pitcher": "matt svanson",
      "result": "In play, no out",
      "pitch": "Sinker"
    },
    "53": {
      "player": "will benson",
      "pitcher": "matt svanson",
      "result": "In play, out(s)",
      "pitch": "Sinker"
    },
    "52": {
      "player": "nolan gorman",
      "pitcher": "graham ashcraft",
      "result": "Called Strike",
      "pitch": "Slider"
    },
    "51": {
      "player": "nolan arenado",
      "pitcher": "brady singer",
      "result": "In play, out(s)",
      "pitch": "Sinker"
    },
    "50": {
      "player": "alec burleson",
      "pitcher": "brady singer",
      "result": "Swinging Strike",
      "pitch": "Sinker"
    },
    "49": {
      "player": "ivan herrera",
      "pitcher": "brady singer",
      "result": "In play, run(s)",
      "pitch": "Slider"
    },
    "48": {
      "player": "lars nootbaar",
      "pitcher": "brady singer",
      "result": "Ball",
      "pitch": "Slider"
    },
    "47": {
      "player": "noelvi marte",
      "pitcher": "jorge alcala",
      "result": "In play, out(s)",
      "pitch": "4-Seam Fastball"
    },
    "46": {
      "player": "gavin lux",
      "pitcher": "jorge alcala",
      "result": "In play, no out",
      "pitch": "Curveball"
    },
    "45": {
      "player": "matt mclain",
      "pitcher": "jorge alcala",
      "result": "Called Strike",
      "pitch": "Sinker"
    },
    "44": {
      "player": "jose trevino",
      "pitcher": "jorge alcala",
      "result": "In play, out(s)",
      "pitch": "Slider"
    },
    "43": {
      "player": "spencer steer",
      "pitcher": "jorge alcala",
      "result": "In play, no out",
      "pitch": "Sinker"
    },
    "42": {
      "player": "victor scott",
      "pitcher": "brady singer",
      "result": "In play, out(s)",
      "pitch": "Cutter"
    },
    "41": {
      "player": "jordan walker",
      "pitcher": "brady singer",
      "result": "In play, out(s)",
      "pitch": "Sweeper"
    },
    "40": {
      "player": "jimmy crooks",
      "pitcher": "brady singer",
      "result": "In play, no out",
      "pitch": "Sinker"
    },
    "39": {
      "player": "thomas saggese",
      "pitcher": "brady singer",
      "result": "Called Strike",
      "pitch": "Sinker"
    },
    "38": {
      "player": "elly de la cruz",
      "pitcher": "andre pallante",
      "result": "In play, out(s)",
      "pitch": "4-Seam Fastball"
    },
    "37": {
      "player": "sal stewart",
      "pitcher": "andre pallante",
      "result": "Ball",
      "pitch": "Slider"
    },
    "36": {
      "player": "austin hays",
      "pitcher": "andre pallante",
      "result": "In play, out(s)",
      "pitch": "4-Seam Fastball"
    },
    "35": {
      "player": "will benson",
      "pitcher": "andre pallante",
      "result": "In play, out(s)",
      "pitch": "4-Seam Fastball"
    },
    "34": {
      "player": "noelvi marte",
      "pitcher": "andre pallante",
      "result": "In play, no out",
      "pitch": "Sinker"
    },
    "33": {
      "player": "gavin lux",
      "pitcher": "andre pallante",
      "result": "In play, no out",
      "pitch": "4-Seam Fastball"
    },
    "32": {
      "player": "nolan gorman",
      "pitcher": "brady singer",
      "result": "Swinging Strike",
      "pitch": "Sinker"
    },
    "31": {
      "player": "nolan arenado",
      "pitcher": "brady singer",
      "result": "In play, out(s)",
      "pitch": "Sinker"
    },
    "30": {
      "player": "alec burleson",
      "pitcher": "brady singer",
      "result": "In play, no out",
      "pitch": "Slider"
    },
    "29": {
      "player": "matt mclain",
      "pitcher": "andre pallante",
      "result": "In play, out(s)",
      "pitch": "Sinker"
    },
    "28": {
      "player": "jose trevino",
      "pitcher": "andre pallante",
      "result": "In play, out(s)",
      "pitch": "Slider"
    },
    "27": {
      "player": "spencer steer",
      "pitcher": "andre pallante",
      "result": "In play, run(s)",
      "pitch": "4-Seam Fastball"
    },
    "26": {
      "player": "elly de la cruz",
      "pitcher": "andre pallante",
      "result": "Ball",
      "pitch": "4-Seam Fastball"
    },
    "25": {
      "player": "sal stewart",
      "pitcher": "andre pallante",
      "result": "Ball",
      "pitch": "Slider"
    },
    "24": {
      "player": "austin hays",
      "pitcher": "andre pallante",
      "result": "In play, out(s)",
      "pitch": "Knuckle Curve"
    },
    "23": {
      "player": "ivan herrera",
      "pitcher": "brady singer",
      "result": "In play, out(s)",
      "pitch": "Slider"
    },
    "22": {
      "player": "lars nootbaar",
      "pitcher": "brady singer",
      "result": "Swinging Strike",
      "pitch": "Slider"
    },
    "21": {
      "player": "victor scott",
      "pitcher": "brady singer",
      "result": "Ball",
      "pitch": "Sinker"
    },
    "20": {
      "player": "jordan walker",
      "pitcher": "brady singer",
      "result": "Called Strike",
      "pitch": "Slider"
    },
    "19": {
      "player": "will benson",
      "pitcher": "andre pallante",
      "result": "In play, out(s)",
      "pitch": "4-Seam Fastball"
    },
    "18": {
      "player": "noelvi marte",
      "pitcher": "andre pallante",
      "result": "In play, no out",
      "pitch": "Slider"
    },
    "17": {
      "player": "gavin lux",
      "pitcher": "andre pallante",
      "result": "In play, out(s)",
      "pitch": "4-Seam Fastball"
    },
    "16": {
      "player": "matt mclain",
      "pitcher": "andre pallante",
      "result": "Swinging Strike",
      "pitch": "Slider"
    },
    "15": {
      "player": "jose trevino",
      "pitcher": "andre pallante",
      "result": "In play, no out",
      "pitch": "Sinker"
    },
    "14": {
      "player": "jimmy crooks",
      "pitcher": "brady singer",
      "result": "In play, out(s)",
      "pitch": "Slider"
    },
    "13": {
      "player": "thomas saggese",
      "pitcher": "brady singer",
      "result": "In play, out(s)",
      "pitch": "Slider"
    },
    "12": {
      "player": "nolan gorman",
      "pitcher": "brady singer",
      "result": "In play, out(s)",
      "pitch": "Slider"
    },
    "11": {
      "player": "spencer steer",
      "pitcher": "andre pallante",
      "result": "In play, out(s)",
      "pitch": "Sinker"
    },
    "10": {
      "player": "elly de la cruz",
      "pitcher": "andre pallante",
      "result": "Swinging Strike",
      "pitch": "4-Seam Fastball"
    },
    "9": {
      "player": "sal stewart",
      "pitcher": "andre pallante",
      "result": "In play, out(s)",
      "pitch": "4-Seam Fastball"
    },
    "8": {
      "player": "nolan arenado",
      "pitcher": "brady singer",
      "result": "Swinging Strike",
      "pitch": "Slider"
    },
    "7": {
      "player": "alec burleson",
      "pitcher": "brady singer",
      "result": "In play, run(s)",
      "pitch": "Sinker"
    },
    "6": {
      "player": "ivan herrera",
      "pitcher": "brady singer",
      "result": "In play, out(s)",
      "pitch": "Sinker"
    },
    "5": {
      "player": "lars nootbaar",
      "pitcher": "brady singer",
      "result": "In play, out(s)",
      "pitch": "Sinker"
    },
    "4": {
      "player": "austin hays",
      "pitcher": "andre pallante",
      "result": "In play, out(s)",
      "pitch": "Sinker"
    },
    "3": {
      "player": "will benson",
      "pitcher": "andre pallante",
      "result": "In play, out(s)",
      "pitch": "4-Seam Fastball"
    },
    "2": {
      "player": "noelvi marte",
      "pitcher": "andre pallante",
      "result": "Called Strike",
      "pitch": "Knuckle Curve"
    },
    "1": {
      "player": "gavin lux",
      "pitcher": "andre pallante",
      "result": "In play, no out",
      "pitch": "Slider"
    }
  },
  "bal @ chw": {
    "68": {
      "player": "curtis mead",
      "pitcher": "keegan akin",
      "result": "Foul",
      "pitch": "4-Seam Fastball"
    },
    "67": {
      "player": "chase meidroth",
      "pitcher": "keegan akin",
      "result": "In play, no out",
      "pitch": "Changeup"
    },
    "66": {
      "player": "gunnar henderson",
      "pitcher": "tyler gilbert",
      "result": "Swinging Strike",
      "pitch": "Sweeper"
    },
    "65": {
      "player": "jordan westburg",
      "pitcher": "brandon eisert",
      "result": "In play, out(s)",
      "pitch": "Changeup"
    },
    "64": {
      "player": "jackson holliday",
      "pitcher": "brandon eisert",
      "result": "Swinging Strike",
      "pitch": "Slider"
    },
    "63": {
      "player": "jorge mateo",
      "pitcher": "brandon eisert",
      "result": "In play, no out",
      "pitch": "Changeup"
    },
    "62": {
      "player": "alex jackson",
      "pitcher": "brandon eisert",
      "result": "Ball",
      "pitch": "4-Seam Fastball"
    },
    "61": {
      "player": "dominic fletcher",
      "pitcher": "rico garcia",
      "result": "In play, out(s)",
      "pitch": "Changeup"
    },
    "60": {
      "player": "kyle teel",
      "pitcher": "rico garcia",
      "result": "Swinging Strike",
      "pitch": "Changeup"
    },
    "59": {
      "player": "will robertson",
      "pitcher": "rico garcia",
      "result": "In play, out(s)",
      "pitch": "Changeup"
    },
    "58": {
      "player": "dylan beavers",
      "pitcher": "brandon eisert",
      "result": "In play, out(s)",
      "pitch": "Slider"
    },
    "57": {
      "player": "coby mayo",
      "pitcher": "jordan leasure",
      "result": "In play, out(s)",
      "pitch": "Slider"
    },
    "56": {
      "player": "jeremiah jackson",
      "pitcher": "jordan leasure",
      "result": "In play, out(s)",
      "pitch": "Slider"
    },
    "55": {
      "player": "lenyn sosa",
      "pitcher": "yaramil hiraldo",
      "result": "Swinging Strike",
      "pitch": "4-Seam Fastball"
    },
    "54": {
      "player": "edgar quero",
      "pitcher": "yaramil hiraldo",
      "result": "In play, out(s)",
      "pitch": "Changeup"
    },
    "53": {
      "player": "colson montgomery",
      "pitcher": "yaramil hiraldo",
      "result": "In play, out(s)",
      "pitch": "4-Seam Fastball"
    },
    "52": {
      "player": "tyler oneill",
      "pitcher": "jordan leasure",
      "result": "Called Strike",
      "pitch": "Slider"
    },
    "51": {
      "player": "gunnar henderson",
      "pitcher": "jordan leasure",
      "result": "In play, out(s)",
      "pitch": "4-Seam Fastball"
    },
    "50": {
      "player": "jordan westburg",
      "pitcher": "jordan leasure",
      "result": "In play, out(s)",
      "pitch": "4-Seam Fastball"
    },
    "49": {
      "player": "miguel vargas",
      "pitcher": "tyler wells",
      "result": "In play, out(s)",
      "pitch": "Changeup"
    },
    "48": {
      "player": "mike tauchman",
      "pitcher": "tyler wells",
      "result": "Swinging Strike",
      "pitch": "4-Seam Fastball"
    },
    "47": {
      "player": "chase meidroth",
      "pitcher": "tyler wells",
      "result": "In play, out(s)",
      "pitch": "Changeup"
    },
    "46": {
      "player": "jackson holliday",
      "pitcher": "grant taylor",
      "result": "Swinging Strike",
      "pitch": "4-Seam Fastball"
    },
    "45": {
      "player": "jorge mateo",
      "pitcher": "grant taylor",
      "result": "Swinging Strike",
      "pitch": "Curveball"
    },
    "44": {
      "player": "alex jackson",
      "pitcher": "grant taylor",
      "result": "Swinging Strike",
      "pitch": "4-Seam Fastball"
    },
    "43": {
      "player": "dylan beavers",
      "pitcher": "grant taylor",
      "result": "Ball",
      "pitch": "Cutter"
    },
    "42": {
      "player": "dominic fletcher",
      "pitcher": "tyler wells",
      "result": "In play, out(s)",
      "pitch": "Changeup"
    },
    "41": {
      "player": "michael a taylor",
      "pitcher": "tyler wells",
      "result": "In play, out(s)",
      "pitch": "Changeup"
    },
    "40": {
      "player": "will robertson",
      "pitcher": "tyler wells",
      "result": "Swinging Strike",
      "pitch": "Cutter"
    },
    "39": {
      "player": "coby mayo",
      "pitcher": "steven wilson",
      "result": "Swinging Strike",
      "pitch": "4-Seam Fastball"
    },
    "38": {
      "player": "jeremiah jackson",
      "pitcher": "steven wilson",
      "result": "Swinging Strike",
      "pitch": "Sweeper"
    },
    "37": {
      "player": "tyler oneill",
      "pitcher": "steven wilson",
      "result": "Ball",
      "pitch": "Sweeper"
    },
    "36": {
      "player": "gunnar henderson",
      "pitcher": "steven wilson",
      "result": "In play, no out",
      "pitch": "Cutter"
    },
    "35": {
      "player": "jordan westburg",
      "pitcher": "steven wilson",
      "result": "Called Strike",
      "pitch": "Sweeper"
    },
    "34": {
      "player": "lenyn sosa",
      "pitcher": "tyler wells",
      "result": "In play, out(s)",
      "pitch": "4-Seam Fastball"
    },
    "33": {
      "player": "edgar quero",
      "pitcher": "tyler wells",
      "result": "In play, no out",
      "pitch": "Slider"
    },
    "32": {
      "player": "colson montgomery",
      "pitcher": "tyler wells",
      "result": "In play, out(s)",
      "pitch": "Cutter"
    },
    "31": {
      "player": "miguel vargas",
      "pitcher": "tyler wells",
      "result": "In play, out(s)",
      "pitch": "Curveball"
    },
    "30": {
      "player": "mike tauchman",
      "pitcher": "tyler wells",
      "result": "In play, run(s)",
      "pitch": "Slider"
    },
    "29": {
      "player": "jackson holliday",
      "pitcher": "steven wilson",
      "result": "Called Strike",
      "pitch": "Sweeper"
    },
    "28": {
      "player": "jorge mateo",
      "pitcher": "martin perez",
      "result": "In play, no out",
      "pitch": "Changeup"
    },
    "27": {
      "player": "alex jackson",
      "pitcher": "martin perez",
      "result": "Called Strike",
      "pitch": "Cutter"
    },
    "26": {
      "player": "dylan beavers",
      "pitcher": "martin perez",
      "result": "In play, run(s)",
      "pitch": "Sinker"
    },
    "25": {
      "player": "coby mayo",
      "pitcher": "martin perez",
      "result": "In play, no out",
      "pitch": "Sinker"
    },
    "24": {
      "player": "jeremiah jackson",
      "pitcher": "martin perez",
      "result": "In play, out(s)",
      "pitch": "Sinker"
    },
    "23": {
      "player": "chase meidroth",
      "pitcher": "tyler wells",
      "result": "In play, out(s)",
      "pitch": "4-Seam Fastball"
    },
    "22": {
      "player": "dominic fletcher",
      "pitcher": "tyler wells",
      "result": "In play, out(s)",
      "pitch": "Changeup"
    },
    "21": {
      "player": "michael a taylor",
      "pitcher": "tyler wells",
      "result": "In play, out(s)",
      "pitch": "4-Seam Fastball"
    },
    "20": {
      "player": "tyler oneill",
      "pitcher": "martin perez",
      "result": "In play, out(s)",
      "pitch": "Changeup"
    },
    "19": {
      "player": "gunnar henderson",
      "pitcher": "martin perez",
      "result": "In play, out(s)",
      "pitch": "Curveball"
    },
    "18": {
      "player": "jordan westburg",
      "pitcher": "martin perez",
      "result": "In play, out(s)",
      "pitch": "Cutter"
    },
    "17": {
      "player": "will robertson",
      "pitcher": "tyler wells",
      "result": "In play, out(s)",
      "pitch": "Changeup"
    },
    "16": {
      "player": "lenyn sosa",
      "pitcher": "tyler wells",
      "result": "In play, out(s)",
      "pitch": "Cutter"
    },
    "15": {
      "player": "edgar quero",
      "pitcher": "tyler wells",
      "result": "In play, no out",
      "pitch": "Curveball"
    },
    "14": {
      "player": "colson montgomery",
      "pitcher": "tyler wells",
      "result": "In play, no out",
      "pitch": "4-Seam Fastball"
    },
    "13": {
      "player": "jackson holliday",
      "pitcher": "martin perez",
      "result": "In play, out(s)",
      "pitch": "Sinker"
    },
    "12": {
      "player": "jorge mateo",
      "pitcher": "martin perez",
      "result": "In play, out(s)",
      "pitch": "Cutter"
    },
    "11": {
      "player": "alex jackson",
      "pitcher": "martin perez",
      "result": "In play, out(s)",
      "pitch": "Changeup"
    },
    "10": {
      "player": "miguel vargas",
      "pitcher": "tyler wells",
      "result": "Called Strike",
      "pitch": "Cutter"
    },
    "9": {
      "player": "mike tauchman",
      "pitcher": "tyler wells",
      "result": "Swinging Strike",
      "pitch": "4-Seam Fastball"
    },
    "8": {
      "player": "chase meidroth",
      "pitcher": "tyler wells",
      "result": "In play, out(s)",
      "pitch": "Cutter"
    },
    "7": {
      "player": "dylan beavers",
      "pitcher": "martin perez",
      "result": "In play, out(s)",
      "pitch": "Changeup"
    },
    "6": {
      "player": "coby mayo",
      "pitcher": "martin perez",
      "result": "Ball",
      "pitch": "Changeup"
    },
    "5": {
      "player": "jeremiah jackson",
      "pitcher": "martin perez",
      "result": "In play, run(s)",
      "pitch": "Cutter"
    },
    "4": {
      "player": "tyler oneill",
      "pitcher": "martin perez",
      "result": "Ball",
      "pitch": "Sinker"
    },
    "3": {
      "player": "gunnar henderson",
      "pitcher": "martin perez",
      "result": "In play, no out",
      "pitch": "Cutter"
    },
    "2": {
      "player": "jordan westburg",
      "pitcher": "martin perez",
      "result": "Swinging Strike",
      "pitch": "Changeup"
    },
    "1": {
      "player": "jackson holliday",
      "pitcher": "martin perez",
      "result": "In play, out(s)",
      "pitch": "Cutter"
    }
  },
  "sf @ ari": {
    "29": {
      "player": "jerar encarnacion",
      "pitcher": "brandon pfaadt",
      "result": "Ball",
      "pitch": "Sinker"
    },
    "28": {
      "player": "bryce eldridge",
      "pitcher": "brandon pfaadt",
      "result": "Swinging Strike",
      "pitch": "4-Seam Fastball"
    },
    "27": {
      "player": "blaze alexander",
      "pitcher": "justin verlander",
      "result": "Swinging Strike",
      "pitch": "4-Seam Fastball"
    },
    "26": {
      "player": "gabriel moreno",
      "pitcher": "justin verlander",
      "result": "In play, out(s)",
      "pitch": "Slider"
    },
    "25": {
      "player": "corbin carroll",
      "pitcher": "justin verlander",
      "result": "Ball In Dirt",
      "pitch": "Slider"
    },
    "24": {
      "player": "ketel marte",
      "pitcher": "justin verlander",
      "result": "In play, out(s)",
      "pitch": "4-Seam Fastball"
    },
    "23": {
      "player": "geraldo perdomo",
      "pitcher": "justin verlander",
      "result": "In play, no out",
      "pitch": "4-Seam Fastball"
    },
    "22": {
      "player": "matt chapman",
      "pitcher": "brandon pfaadt",
      "result": "In play, out(s)",
      "pitch": "Sinker"
    },
    "21": {
      "player": "willy adames",
      "pitcher": "brandon pfaadt",
      "result": "In play, out(s)",
      "pitch": "Sweeper"
    },
    "20": {
      "player": "rafael devers",
      "pitcher": "brandon pfaadt",
      "result": "In play, out(s)",
      "pitch": "4-Seam Fastball"
    },
    "19": {
      "player": "jake mccarthy",
      "pitcher": "justin verlander",
      "result": "In play, out(s)",
      "pitch": "Slider"
    },
    "18": {
      "player": "tim tawa",
      "pitcher": "justin verlander",
      "result": "In play, out(s)",
      "pitch": "Slider"
    },
    "17": {
      "player": "alek thomas",
      "pitcher": "justin verlander",
      "result": "In play, out(s)",
      "pitch": "Slider"
    },
    "16": {
      "player": "heliot ramos",
      "pitcher": "brandon pfaadt",
      "result": "In play, out(s)",
      "pitch": "Sinker"
    },
    "15": {
      "player": "drew gilbert",
      "pitcher": "brandon pfaadt",
      "result": "In play, out(s)",
      "pitch": "4-Seam Fastball"
    },
    "14": {
      "player": "christian koss",
      "pitcher": "brandon pfaadt",
      "result": "In play, out(s)",
      "pitch": "Sinker"
    },
    "13": {
      "player": "james mccann",
      "pitcher": "justin verlander",
      "result": "Swinging Strike",
      "pitch": "4-Seam Fastball"
    },
    "12": {
      "player": "blaze alexander",
      "pitcher": "justin verlander",
      "result": "In play, no out",
      "pitch": "Curveball"
    },
    "11": {
      "player": "gabriel moreno",
      "pitcher": "justin verlander",
      "result": "In play, out(s)",
      "pitch": "4-Seam Fastball"
    },
    "10": {
      "player": "patrick bailey",
      "pitcher": "brandon pfaadt",
      "result": "In play, out(s)",
      "pitch": "Changeup"
    },
    "9": {
      "player": "jerar encarnacion",
      "pitcher": "brandon pfaadt",
      "result": "Swinging Strike",
      "pitch": "Sweeper"
    },
    "8": {
      "player": "bryce eldridge",
      "pitcher": "brandon pfaadt",
      "result": "Swinging Strike",
      "pitch": "4-Seam Fastball"
    },
    "7": {
      "player": "corbin carroll",
      "pitcher": "justin verlander",
      "result": "In play, out(s)",
      "pitch": "4-Seam Fastball"
    },
    "6": {
      "player": "ketel marte",
      "pitcher": "justin verlander",
      "result": "In play, out(s)",
      "pitch": "Curveball"
    },
    "5": {
      "player": "geraldo perdomo",
      "pitcher": "justin verlander",
      "result": "In play, out(s)",
      "pitch": "Slider"
    },
    "4": {
      "player": "matt chapman",
      "pitcher": "brandon pfaadt",
      "result": "Foul Tip",
      "pitch": "Sinker"
    },
    "3": {
      "player": "willy adames",
      "pitcher": "brandon pfaadt",
      "result": "Ball",
      "pitch": "4-Seam Fastball"
    },
    "2": {
      "player": "rafael devers",
      "pitcher": "brandon pfaadt",
      "result": "Swinging Strike",
      "pitch": "4-Seam Fastball"
    },
    "1": {
      "player": "heliot ramos",
      "pitcher": "brandon pfaadt",
      "result": "In play, out(s)",
      "pitch": "Cutter"
    }
  },
  "atl @ wsh": {
    "22": {
      "player": "drake baldwin",
      "pitcher": "brad lord",
      "result": "In play, out(s)",
      "pitch": "Changeup"
    },
    "21": {
      "player": "ronald acuna",
      "pitcher": "brad lord",
      "result": "In play, no out",
      "pitch": "Slider"
    },
    "20": {
      "player": "brady house",
      "pitcher": "hurston waldrep",
      "result": "In play, out(s)",
      "pitch": "Cutter"
    },
    "19": {
      "player": "robert hassell",
      "pitcher": "hurston waldrep",
      "result": "Called Strike",
      "pitch": "Curveball"
    },
    "18": {
      "player": "riley adams",
      "pitcher": "hurston waldrep",
      "result": "Swinging Strike",
      "pitch": "Curveball"
    },
    "17": {
      "player": "matt olson",
      "pitcher": "brad lord",
      "result": "In play, out(s)",
      "pitch": "Changeup"
    },
    "16": {
      "player": "jurickson profar",
      "pitcher": "brad lord",
      "result": "In play, out(s)",
      "pitch": "Sinker"
    },
    "15": {
      "player": "nacho alvarez",
      "pitcher": "brad lord",
      "result": "In play, no out",
      "pitch": "Sinker"
    },
    "14": {
      "player": "marcell ozuna",
      "pitcher": "brad lord",
      "result": "In play, no out",
      "pitch": "Sinker"
    },
    "13": {
      "player": "dylan crews",
      "pitcher": "hurston waldrep",
      "result": "In play, out(s)",
      "pitch": "Slider"
    },
    "12": {
      "player": "luis garcia",
      "pitcher": "hurston waldrep",
      "result": "Swinging Strike",
      "pitch": "Curveball"
    },
    "11": {
      "player": "daylen lile",
      "pitcher": "hurston waldrep",
      "result": "Swinging Strike",
      "pitch": "Splitter"
    },
    "10": {
      "player": "michael harris",
      "pitcher": "brad lord",
      "result": "Called Strike",
      "pitch": "Slider"
    },
    "9": {
      "player": "ha seong kim",
      "pitcher": "brad lord",
      "result": "In play, out(s)",
      "pitch": "Slider"
    },
    "8": {
      "player": "ozzie albies",
      "pitcher": "brad lord",
      "result": "Swinging Strike",
      "pitch": "4-Seam Fastball"
    },
    "7": {
      "player": "josh bell",
      "pitcher": "hurston waldrep",
      "result": "Swinging Strike",
      "pitch": "Splitter"
    },
    "6": {
      "player": "cj abrams",
      "pitcher": "hurston waldrep",
      "result": "Swinging Strike",
      "pitch": "Curveball"
    },
    "5": {
      "player": "james wood",
      "pitcher": "hurston waldrep",
      "result": "In play, out(s)",
      "pitch": "Sinker"
    },
    "4": {
      "player": "drake baldwin",
      "pitcher": "brad lord",
      "result": "In play, out(s)",
      "pitch": "Sinker"
    },
    "3": {
      "player": "ronald acuna",
      "pitcher": "brad lord",
      "result": "In play, out(s)",
      "pitch": "4-Seam Fastball"
    },
    "2": {
      "player": "matt olson",
      "pitcher": "brad lord",
      "result": "In play, no out",
      "pitch": "4-Seam Fastball"
    },
    "1": {
      "player": "jurickson profar",
      "pitcher": "brad lord",
      "result": "In play, out(s)",
      "pitch": "Changeup"
    }
  },
  "cle @ det": {},
  "ath @ bos": {},
  "tor @ tb": {},
  "sd @ nym": {},
  "sea @ kc": {},
  "nyy @ min": {},
  "laa @ mil": {},
  "tex @ hou": {},
  "mia @ col": {},
  "phi @ lad": {}
}